[
    {
        "id": "m2123",
        "legs": 3,
        "total_height": 36.83892676380137,
        "radius_bottom": 13.645671683805878,
        "radius_top": 8.682735991085853,
        "n_layers": 4,
        "layer_heights": [
            13.017575937129056,
            18.09884705469489
        ],
        "connection_types": [
            "NONE",
            "NONE",
            "NONE"
        ],
        "Cost": 156.63199934982097,
        "plausibility (FAMD GMM)": 7.912425757924758,
        "plausibility (FAMD Mahalanobis)": 0.7578728221115938,
        "plausibility (SVM)": 0.5246742376975484,
        "plausibility (One Class SVM) gamma=scale nu=0.5": 8.166625301799005,
        "plausibility (FAMD One Class SVM) gamma=scale nu=0.5": 1.4811165386387994,
        "wave": 1241935.2331448873,
        "combined": 43906898.82766418,
        "compression": 39626648.55355089,
        "tipover": 4205858.835124094,
        "torque": 2411857.8305464713
    },
    {
        "id": "c10524",
        "legs": 4,
        "total_height": 92.22061323184838,
        "radius_bottom": 13.645671683805878,
        "radius_top": 10.035792439640886,
        "n_layers": 4,
        "layer_heights": [
            15.84353493023512,
            22.674884523459635
        ],
        "connection_types": [
            "NONE",
            "NONE",
            "NONE"
        ],
        "Cost": 425.9359697409396,
        "plausibility (FAMD GMM)": 2.8319046196258326,
        "plausibility (FAMD Mahalanobis)": 1.2069670783725985,
        "plausibility (SVM)": 1.793068205173166,
        "plausibility (One Class SVM) gamma=scale nu=0.5": 10.187760593978384,
        "plausibility (FAMD One Class SVM) gamma=scale nu=0.5": 0.17111857154612586,
        "wave": 2001839.0113388204,
        "combined": 35768976.44197251,
        "compression": 27138854.56954604,
        "tipover": 8501271.534017924,
        "torque": 1712771.779999505
    },
    {
        "id": "m1839",
        "legs": 3,
        "total_height": 18.708731431281286,
        "radius_bottom": 19.468142819332982,
        "radius_top": 8.213346913836146,
        "n_layers": 3,
        "layer_heights": [
            7.839348015471635
        ],
        "connection_types": [
            "NONE",
            "Z"
        ],
        "Cost": 176.87618050233024,
        "plausibility (FAMD GMM)": 3.1354037521672384,
        "plausibility (FAMD Mahalanobis)": 1.219890438354867,
        "plausibility (SVM)": -0.36087946351368805,
        "plausibility (One Class SVM) gamma=scale nu=0.5": 10.597908941533682,
        "plausibility (FAMD One Class SVM) gamma=scale nu=0.5": 2.0535012342115966,
        "wave": 623045.6420045521,
        "combined": 83324013.95151761,
        "compression": 83159034.09956929,
        "tipover": 1730468.012929222,
        "torque": 1178177.658699696
    },
    {
        "id": "c11570",
        "legs": 4,
        "total_height": 92.22061323184838,
        "radius_bottom": 13.645671683805878,
        "radius_top": 10.035792439640886,
        "n_layers": 4,
        "layer_heights": [
            6.543736277263741,
            22.674884523459635
        ],
        "connection_types": [
            "NONE",
            "NONE",
            "NONE"
        ],
        "Cost": 425.9359697409396,
        "plausibility (FAMD GMM)": 2.763260336365945,
        "plausibility (FAMD Mahalanobis)": 1.3789978075655918,
        "plausibility (SVM)": 1.8017535996153051,
        "plausibility (One Class SVM) gamma=scale nu=0.5": 10.224804207595941,
        "plausibility (FAMD One Class SVM) gamma=scale nu=0.5": 0.7385350420215229,
        "wave": 2001839.0113388693,
        "combined": 35768976.44197231,
        "compression": 27138854.569545932,
        "tipover": 8501271.534017708,
        "torque": 1712771.7799994901
    },
    {
        "id": "c8910",
        "legs": 4,
        "total_height": 61.67935844569783,
        "radius_bottom": 14.21440039438904,
        "radius_top": 12.591484647035323,
        "n_layers": 3,
        "layer_heights": [
            56.53106720121572
        ],
        "connection_types": [
            "K",
            "K"
        ],
        "Cost": 1010.7369348375,
        "plausibility (FAMD GMM)": 5.6264553365202,
        "plausibility (FAMD Mahalanobis)": 1.255137702053457,
        "plausibility (SVM)": 1.414708260732747,
        "plausibility (One Class SVM) gamma=scale nu=0.5": 9.659725039063987,
        "plausibility (FAMD One Class SVM) gamma=scale nu=0.5": 0.5944600976660439,
        "wave": 599841.7345433787,
        "combined": 15767010.679241829,
        "compression": 15370650.886781637,
        "tipover": 637159.908097669,
        "torque": 202142.95838652825
    },
    {
        "id": "c9243",
        "legs": 3,
        "total_height": 18.708731431281286,
        "radius_bottom": 13.645671683805878,
        "radius_top": 8.375906891368846,
        "n_layers": 4,
        "layer_heights": [
            9.661310646468777,
            18.676170579105044
        ],
        "connection_types": [
            "NONE",
            "NONE",
            "NONE"
        ],
        "Cost": 101.83272361896195,
        "plausibility (FAMD GMM)": 5.288489769431438,
        "plausibility (FAMD Mahalanobis)": 1.6642342908868937,
        "plausibility (SVM)": 0.13238819220192477,
        "plausibility (One Class SVM) gamma=scale nu=0.5": 10.592618289517754,
        "plausibility (FAMD One Class SVM) gamma=scale nu=0.5": 2.304111136559465,
        "wave": 847498.1385290927,
        "combined": 51466586.22255787,
        "compression": 49258754.832330234,
        "tipover": 2198069.051490149,
        "torque": 1734197.4420555993
    },
    {
        "id": "m452",
        "legs": 4,
        "total_height": 69.59776304183762,
        "radius_bottom": 14.21440039438904,
        "radius_top": 12.591484647035323,
        "n_layers": 3,
        "layer_heights": [
            56.53106720121572
        ],
        "connection_types": [
            "K",
            "K"
        ],
        "Cost": 1087.7165686227384,
        "plausibility (FAMD GMM)": 3.4933849644984556,
        "plausibility (FAMD Mahalanobis)": 0.9772577600399054,
        "plausibility (SVM)": 1.5611660166141612,
        "plausibility (One Class SVM) gamma=scale nu=0.5": 10.073020614504212,
        "plausibility (FAMD One Class SVM) gamma=scale nu=0.5": 0.3968856783367638,
        "wave": 498842.69655624987,
        "combined": 15868073.852886776,
        "compression": 15294197.257388478,
        "tipover": 665326.6967581299,
        "torque": 192779.67918481404
    },
    {
        "id": "m2318",
        "legs": 4,
        "total_height": 82.52687027810286,
        "radius_bottom": 25.262493553913206,
        "radius_top": 9.203634873877972,
        "n_layers": 5,
        "layer_heights": [
            13.017575937129056,
            26.935035634133214,
            45.43344011499657
        ],
        "connection_types": [
            "X",
            "XH",
            "K",
            "X"
        ],
        "Cost": 1809.9375895309074,
        "plausibility (FAMD GMM)": 3.3409919572627405,
        "plausibility (FAMD Mahalanobis)": 1.7707816869498463,
        "plausibility (SVM)": -0.49721094732942595,
        "plausibility (One Class SVM) gamma=scale nu=0.5": 7.952233342024089,
        "plausibility (FAMD One Class SVM) gamma=scale nu=0.5": 2.3501703619614123,
        "wave": 87025.80269681479,
        "combined": 35931427.089814715,
        "compression": 35895729.184181154,
        "tipover": 440552.6407111804,
        "torque": 62442.76903136557
    },
    {
        "id": "c10494",
        "legs": 4,
        "total_height": 82.52687027810286,
        "radius_bottom": 25.262493553913206,
        "radius_top": 9.203634873877972,
        "n_layers": 4,
        "layer_heights": [
            16.172889027369262,
            45.43344011499657
        ],
        "connection_types": [
            "K",
            "K",
            "K"
        ],
        "Cost": 1488.0493044234472,
        "plausibility (FAMD GMM)": 6.755832572444021,
        "plausibility (FAMD Mahalanobis)": 1.111275856520289,
        "plausibility (SVM)": 0.45422257641088004,
        "plausibility (One Class SVM) gamma=scale nu=0.5": 8.513217497588077,
        "plausibility (FAMD One Class SVM) gamma=scale nu=0.5": 0.4331342916511005,
        "wave": 53679.35612070605,
        "combined": 27870976.56421047,
        "compression": 27831823.053411983,
        "tipover": 368974.6240937623,
        "torque": 72727.23645099142
    },
    {
        "id": "m594",
        "legs": 4,
        "total_height": 61.67935844569783,
        "radius_bottom": 19.468142819332982,
        "radius_top": 9.203634873877972,
        "n_layers": 4,
        "layer_heights": [
            22.674884523459635,
            40.71398998887875
        ],
        "connection_types": [
            "X",
            "X",
            "X"
        ],
        "Cost": 998.2255302829343,
        "plausibility (FAMD GMM)": 4.004738596216256,
        "plausibility (FAMD Mahalanobis)": 0.05606015090292978,
        "plausibility (SVM)": -1.4840573924083933,
        "plausibility (One Class SVM) gamma=scale nu=0.5": -3.286186034949452,
        "plausibility (FAMD One Class SVM) gamma=scale nu=0.5": -0.2777214069400298,
        "wave": 93794.79423132498,
        "combined": 35171457.67712012,
        "compression": 35212524.13830662,
        "tipover": 433875.72474290425,
        "torque": 74260.1758169683
    },
    {
        "id": "c9502",
        "legs": 4,
        "total_height": 18.708731431281286,
        "radius_bottom": 27.848412247942864,
        "radius_top": 9.203634873877972,
        "n_layers": 4,
        "layer_heights": [
            16.172889027369262,
            17.544416393260803
        ],
        "connection_types": [
            "K",
            "X",
            "X"
        ],
        "Cost": 723.8603467631217,
        "plausibility (FAMD GMM)": 3.1398887771495296,
        "plausibility (FAMD Mahalanobis)": 1.5268945645700918,
        "plausibility (SVM)": -2.4147676976474535,
        "plausibility (One Class SVM) gamma=scale nu=0.5": 10.401460420125764,
        "plausibility (FAMD One Class SVM) gamma=scale nu=0.5": 2.00538435215611,
        "wave": 275118.7950210139,
        "combined": 54820949.99719266,
        "compression": 55080445.765909664,
        "tipover": 172948.60332199966,
        "torque": 67983.6500984248
    },
    {
        "id": "c11249",
        "legs": 4,
        "total_height": 41.79608223523681,
        "radius_bottom": 27.848412247942864,
        "radius_top": 12.591484647035323,
        "n_layers": 4,
        "layer_heights": [
            22.674884523459635,
            26.728884247510326
        ],
        "connection_types": [
            "X",
            "K",
            "X"
        ],
        "Cost": 1008.3860556435518,
        "plausibility (FAMD GMM)": 0.5894651529913848,
        "plausibility (FAMD Mahalanobis)": 0.7786886763175204,
        "plausibility (SVM)": -1.369756733867907,
        "plausibility (One Class SVM) gamma=scale nu=0.5": 7.35304550665337,
        "plausibility (FAMD One Class SVM) gamma=scale nu=0.5": -0.20854778142275698,
        "wave": 71177.98338943192,
        "combined": 50458800.551061235,
        "compression": 50689138.430907965,
        "tipover": 305484.4726991999,
        "torque": 49007.85747485737
    },
    {
        "id": "c11647",
        "legs": 3,
        "total_height": 18.708731431281286,
        "radius_bottom": 27.848412247942864,
        "radius_top": 9.203634873877972,
        "n_layers": 4,
        "layer_heights": [
            15.84353493023512,
            18.61472307387897
        ],
        "connection_types": [
            "X",
            "X",
            "NONE"
        ],
        "Cost": 472.55962699837335,
        "plausibility (FAMD GMM)": 2.994201733363902,
        "plausibility (FAMD Mahalanobis)": 1.5788576964927175,
        "plausibility (SVM)": -2.547081429294655,
        "plausibility (One Class SVM) gamma=scale nu=0.5": 10.587596267794805,
        "plausibility (FAMD One Class SVM) gamma=scale nu=0.5": 2.183370963168567,
        "wave": 292499.02313625754,
        "combined": 139711227.60395482,
        "compression": 139230107.3037497,
        "tipover": 549677.9763367558,
        "torque": 82299.50812488844
    },
    {
        "id": "c11342",
        "legs": 3,
        "total_height": 18.708731431281286,
        "radius_bottom": 22.441147571929765,
        "radius_top": 4.32622138384015,
        "n_layers": 4,
        "layer_heights": [
            10.197290965625525,
            15.84353493023512
        ],
        "connection_types": [
            "X",
            "X",
            "NONE"
        ],
        "Cost": 403.70958961068607,
        "plausibility (FAMD GMM)": 3.8416753549122964,
        "plausibility (FAMD Mahalanobis)": 1.3074614456452396,
        "plausibility (SVM)": -2.674303421717402,
        "plausibility (One Class SVM) gamma=scale nu=0.5": 10.228130060211353,
        "plausibility (FAMD One Class SVM) gamma=scale nu=0.5": 1.2766192019282379,
        "wave": 148603.92846574652,
        "combined": 126943599.40232536,
        "compression": 126493663.84981681,
        "tipover": 570171.5795761112,
        "torque": 132955.8536345814
    },
    {
        "id": "m1975",
        "legs": 4,
        "total_height": 18.708731431281286,
        "radius_bottom": 27.848412247942864,
        "radius_top": 8.213346913836146,
        "n_layers": 4,
        "layer_heights": [
            15.84353493023512,
            17.544416393260803
        ],
        "connection_types": [
            "X",
            "X",
            "ZH"
        ],
        "Cost": 648.2244703480399,
        "plausibility (FAMD GMM)": 3.1099995368517304,
        "plausibility (FAMD Mahalanobis)": 1.5223417570588305,
        "plausibility (SVM)": -2.5408357146404277,
        "plausibility (One Class SVM) gamma=scale nu=0.5": 10.151154655480543,
        "plausibility (FAMD One Class SVM) gamma=scale nu=0.5": 1.7223764775537287,
        "wave": 271895.70958638535,
        "combined": 110177350.01435998,
        "compression": 109846456.1049676,
        "tipover": 293173.04230530164,
        "torque": 53038.7808383703
    },
    {
        "id": "c11190",
        "legs": 3,
        "total_height": 18.708731431281286,
        "radius_bottom": 22.441147571929765,
        "radius_top": 10.035792439640886,
        "n_layers": 4,
        "layer_heights": [
            14.71134409405373,
            15.84353493023512
        ],
        "connection_types": [
            "NONE",
            "NONE",
            "NONE"
        ],
        "Cost": 119.49129094729395,
        "plausibility (FAMD GMM)": 4.484455159356463,
        "plausibility (FAMD Mahalanobis)": 1.3416383279576336,
        "plausibility (SVM)": -0.4318977342215553,
        "plausibility (One Class SVM) gamma=scale nu=0.5": 10.507592559684392,
        "plausibility (FAMD One Class SVM) gamma=scale nu=0.5": 0.7569454583507014,
        "wave": 831055.4862863744,
        "combined": 90029960.51347446,
        "compression": 88821153.20948724,
        "tipover": 1965596.8111029526,
        "torque": 1300470.3734022111
    },
    {
        "id": "m1608",
        "legs": 3,
        "total_height": 18.708731431281286,
        "radius_bottom": 22.441147571929765,
        "radius_top": 4.32622138384015,
        "n_layers": 4,
        "layer_heights": [
            10.197290965625525,
            13.017575937129056
        ],
        "connection_types": [
            "X",
            "X",
            "NONE"
        ],
        "Cost": 412.72521921522593,
        "plausibility (FAMD GMM)": 2.6277221150805414,
        "plausibility (FAMD Mahalanobis)": 1.1241838379565354,
        "plausibility (SVM)": -2.6724470011383707,
        "plausibility (One Class SVM) gamma=scale nu=0.5": 10.232344994449566,
        "plausibility (FAMD One Class SVM) gamma=scale nu=0.5": 1.4051891604737534,
        "wave": 139688.54859255042,
        "combined": 132578013.81097378,
        "compression": 132170561.0419275,
        "tipover": 571030.7925087988,
        "torque": 104397.43970811114
    },
    {
        "id": "c11520",
        "legs": 3,
        "total_height": 54.34289691123913,
        "radius_bottom": 19.154759644696405,
        "radius_top": 8.682735991085853,
        "n_layers": 4,
        "layer_heights": [
            10.197290965625525,
            50.62808332768375
        ],
        "connection_types": [
            "X",
            "X",
            "X"
        ],
        "Cost": 786.4771442747264,
        "plausibility (FAMD GMM)": 3.159637037356774,
        "plausibility (FAMD Mahalanobis)": 0.2073902900964731,
        "plausibility (SVM)": -1.7552294936976032,
        "plausibility (One Class SVM) gamma=scale nu=0.5": -1.3979067627375095,
        "plausibility (FAMD One Class SVM) gamma=scale nu=0.5": 0.0673995596203465,
        "wave": 202955.1390731591,
        "combined": 45758859.62174176,
        "compression": 45333177.84084541,
        "tipover": 746734.5196861733,
        "torque": 154101.7868464416
    },
    {
        "id": "c11118",
        "legs": 4,
        "total_height": 79.9247665214869,
        "radius_bottom": 16.719480091877646,
        "radius_top": 10.372317292300867,
        "n_layers": 4,
        "layer_heights": [
            6.543736277263741,
            9.661310646468777
        ],
        "connection_types": [
            "NONE",
            "NONE",
            "NONE"
        ],
        "Cost": 379.38027872458093,
        "plausibility (FAMD GMM)": 3.082517205031308,
        "plausibility (FAMD Mahalanobis)": 1.4900851873446421,
        "plausibility (SVM)": 1.3936074206086553,
        "plausibility (One Class SVM) gamma=scale nu=0.5": 7.148775458245703,
        "plausibility (FAMD One Class SVM) gamma=scale nu=0.5": 1.5273037079283096,
        "wave": 1751209.365130131,
        "combined": 34631956.49936833,
        "compression": 27937610.864328712,
        "tipover": 6432556.215162097,
        "torque": 1816195.3136853224
    },
    {
        "id": "m2295",
        "legs": 3,
        "total_height": 36.919118517575356,
        "radius_bottom": 20.994650332340566,
        "radius_top": 8.213346913836146,
        "n_layers": 4,
        "layer_heights": [
            6.557980820588057,
            19.877808441112457
        ],
        "connection_types": [
            "NONE",
            "NONE",
            "NONE"
        ],
        "Cost": 159.88465918713447,
        "plausibility (FAMD GMM)": 6.3359214663089105,
        "plausibility (FAMD Mahalanobis)": 0.3528853846872551,
        "plausibility (SVM)": -0.17062268041482787,
        "plausibility (One Class SVM) gamma=scale nu=0.5": 7.399172687741951,
        "plausibility (FAMD One Class SVM) gamma=scale nu=0.5": -0.10508190316968857,
        "wave": 1093443.1940438964,
        "combined": 57471891.081909284,
        "compression": 54896317.1652571,
        "tipover": 2935682.2555324933,
        "torque": 2066863.7262824255
    },
    {
        "id": "c11363",
        "legs": 3,
        "total_height": 36.83892676380137,
        "radius_bottom": 19.154759644696405,
        "radius_top": 8.213346913836146,
        "n_layers": 4,
        "layer_heights": [
            14.71134409405373,
            15.84353493023512
        ],
        "connection_types": [
            "NONE",
            "NONE",
            "NONE"
        ],
        "Cost": 157.9660904168532,
        "plausibility (FAMD GMM)": 7.366075091106008,
        "plausibility (FAMD Mahalanobis)": 0.36315294321366337,
        "plausibility (SVM)": -0.01724846147012249,
        "plausibility (One Class SVM) gamma=scale nu=0.5": 7.106644699209088,
        "plausibility (FAMD One Class SVM) gamma=scale nu=0.5": 0.39030596903782744,
        "wave": 1116850.8638929322,
        "combined": 53217078.53938603,
        "compression": 50307654.54429908,
        "tipover": 3131322.366539546,
        "torque": 2149067.5480668866
    },
    {
        "id": "m2287",
        "legs": 4,
        "total_height": 79.9247665214869,
        "radius_bottom": 13.32949964427397,
        "radius_top": 10.372317292300867,
        "n_layers": 4,
        "layer_heights": [
            6.543736277263741,
            9.661310646468777
        ],
        "connection_types": [
            "NONE",
            "NONE",
            "NONE"
        ],
        "Cost": 378.5925073740921,
        "plausibility (FAMD GMM)": 2.5349941562080063,
        "plausibility (FAMD Mahalanobis)": 1.4156631769939962,
        "plausibility (SVM)": 1.6754615499862333,
        "plausibility (One Class SVM) gamma=scale nu=0.5": 8.760428425852822,
        "plausibility (FAMD One Class SVM) gamma=scale nu=0.5": 0.5274734152792249,
        "wave": 1845247.7414834178,
        "combined": 35168081.2948889,
        "compression": 27264897.402239244,
        "tipover": 7683786.719496513,
        "torque": 1794126.6574174622
    },
    {
        "id": "c10882",
        "legs": 4,
        "total_height": 92.22061323184838,
        "radius_bottom": 13.645671683805878,
        "radius_top": 9.203634873877972,
        "n_layers": 4,
        "layer_heights": [
            6.543736277263741,
            15.84353493023512
        ],
        "connection_types": [
            "NONE",
            "NONE",
            "NONE"
        ],
        "Cost": 421.3737497114013,
        "plausibility (FAMD GMM)": 2.696296952339253,
        "plausibility (FAMD Mahalanobis)": 1.4573770867859301,
        "plausibility (SVM)": 1.684951832674765,
        "plausibility (One Class SVM) gamma=scale nu=0.5": 10.27553823608431,
        "plausibility (FAMD One Class SVM) gamma=scale nu=0.5": 0.8956648147854747,
        "wave": 1952206.834677912,
        "combined": 35283768.94141314,
        "compression": 27140055.914150175,
        "tipover": 7975883.548963311,
        "torque": 1683880.4451004781
    },
    {
        "id": "m2048",
        "legs": 3,
        "total_height": 19.44671201273131,
        "radius_bottom": 19.154759644696405,
        "radius_top": 8.213346913836146,
        "n_layers": 4,
        "layer_heights": [
            8.148577245037343,
            18.61472307387897
        ],
        "connection_types": [
            "NONE",
            "X",
            "NONE"
        ],
        "Cost": 246.92301902886865,
        "plausibility (FAMD GMM)": 2.9421025027108905,
        "plausibility (FAMD Mahalanobis)": 1.1495746610498412,
        "plausibility (SVM)": -1.0162983627803093,
        "plausibility (One Class SVM) gamma=scale nu=0.5": 8.091355762695956,
        "plausibility (FAMD One Class SVM) gamma=scale nu=0.5": 1.0831604655893816,
        "wave": 475025.7916350566,
        "combined": 85252369.11895469,
        "compression": 84478436.82944903,
        "tipover": 1240276.5160775606,
        "torque": 841092.744561247
    },
    {
        "id": "c11412",
        "legs": 4,
        "total_height": 78.8120885943492,
        "radius_bottom": 19.468142819332982,
        "radius_top": 8.213346913836146,
        "n_layers": 4,
        "layer_heights": [
            22.674884523459635,
            45.43344011499657
        ],
        "connection_types": [
            "X",
            "X",
            "X"
        ],
        "Cost": 1177.4792164837415,
        "plausibility (FAMD GMM)": 6.549149029824498,
        "plausibility (FAMD Mahalanobis)": 0.4711655613133978,
        "plausibility (SVM)": -1.3318370519943463,
        "plausibility (One Class SVM) gamma=scale nu=0.5": -0.513716641295332,
        "plausibility (FAMD One Class SVM) gamma=scale nu=0.5": -0.4579297049399358,
        "wave": 94719.4774897186,
        "combined": 33556292.536297604,
        "compression": 33482817.82033212,
        "tipover": 507173.9328282003,
        "torque": 75535.81476529004
    },
    {
        "id": "c9388",
        "legs": 3,
        "total_height": 18.708731431281286,
        "radius_bottom": 22.346988342521588,
        "radius_top": 8.213346913836146,
        "n_layers": 4,
        "layer_heights": [
            6.543736277263741,
            15.84353493023512
        ],
        "connection_types": [
            "NONE",
            "NONE",
            "NONE"
        ],
        "Cost": 113.01973921828008,
        "plausibility (FAMD GMM)": 1.6106269233706412,
        "plausibility (FAMD Mahalanobis)": 0.7416505605925344,
        "plausibility (SVM)": -0.6398637622157728,
        "plausibility (One Class SVM) gamma=scale nu=0.5": 10.566873557664309,
        "plausibility (FAMD One Class SVM) gamma=scale nu=0.5": 0.6034288277598936,
        "wave": 774317.0415887259,
        "combined": 100577629.88054779,
        "compression": 99745801.27234176,
        "tipover": 1743453.9747384146,
        "torque": 1347894.5940873683
    },
    {
        "id": "c10721",
        "legs": 3,
        "total_height": 61.67935844569783,
        "radius_bottom": 19.468142819332982,
        "radius_top": 8.213346913836146,
        "n_layers": 4,
        "layer_heights": [
            15.84353493023512,
            22.674884523459635
        ],
        "connection_types": [
            "X",
            "X",
            "NONE"
        ],
        "Cost": 611.8196583095212,
        "plausibility (FAMD GMM)": 4.606044068235344,
        "plausibility (FAMD Mahalanobis)": 0.6107721386846395,
        "plausibility (SVM)": -1.095902753230353,
        "plausibility (One Class SVM) gamma=scale nu=0.5": 0.04831623378029448,
        "plausibility (FAMD One Class SVM) gamma=scale nu=0.5": -0.496156925220971,
        "wave": 176454.67823928306,
        "combined": 49278004.9076578,
        "compression": 48480200.42779504,
        "tipover": 1031283.891518649,
        "torque": 216959.21273657453
    },
    {
        "id": "c11093",
        "legs": 4,
        "total_height": 79.9247665214869,
        "radius_bottom": 16.719480091877646,
        "radius_top": 8.682735991085853,
        "n_layers": 4,
        "layer_heights": [
            9.661310646468777,
            10.197290965625525
        ],
        "connection_types": [
            "NONE",
            "X",
            "NONE"
        ],
        "Cost": 548.3435457251037,
        "plausibility (FAMD GMM)": 2.695558983694626,
        "plausibility (FAMD Mahalanobis)": 1.347232364297014,
        "plausibility (SVM)": 0.4562553327886385,
        "plausibility (One Class SVM) gamma=scale nu=0.5": 4.990073014498902,
        "plausibility (FAMD One Class SVM) gamma=scale nu=0.5": 0.5429401252111727,
        "wave": 961720.8223479682,
        "combined": 31539548.05128021,
        "compression": 28705875.629522674,
        "tipover": 3251613.9454213856,
        "torque": 1205218.7283023137
    },
    {
        "id": "c11644",
        "legs": 4,
        "total_height": 92.22061323184838,
        "radius_bottom": 16.719480091877646,
        "radius_top": 10.035792439640886,
        "n_layers": 4,
        "layer_heights": [
            6.543736277263741,
            15.84353493023512
        ],
        "connection_types": [
            "NONE",
            "NONE",
            "NONE"
        ],
        "Cost": 426.62099951890326,
        "plausibility (FAMD GMM)": 3.423133890806354,
        "plausibility (FAMD Mahalanobis)": 1.5735188007756302,
        "plausibility (SVM)": 1.5444793862078634,
        "plausibility (One Class SVM) gamma=scale nu=0.5": 9.005870549424529,
        "plausibility (FAMD One Class SVM) gamma=scale nu=0.5": 2.226966205658508,
        "wave": 1907344.554813939,
        "combined": 35060526.28207123,
        "compression": 27654566.629007038,
        "tipover": 7220050.65252377,
        "torque": 1747495.3040091193
    },
    {
        "id": "m2246",
        "legs": 3,
        "total_height": 61.67935844569783,
        "radius_bottom": 14.21440039438904,
        "radius_top": 12.591484647035323,
        "n_layers": 3,
        "layer_heights": [
            56.53106720121572
        ],
        "connection_types": [
            "K",
            "K"
        ],
        "Cost": 808.476400754985,
        "plausibility (FAMD GMM)": 5.6264553365202,
        "plausibility (FAMD Mahalanobis)": 1.255137702053457,
        "plausibility (SVM)": 1.2998080655762814,
        "plausibility (One Class SVM) gamma=scale nu=0.5": 9.567759761917374,
        "plausibility (FAMD One Class SVM) gamma=scale nu=0.5": 0.5944600976660439,
        "wave": 609618.4669667658,
        "combined": 21316867.505550124,
        "compression": 20690630.111763723,
        "tipover": 960234.0709039086,
        "torque": 341101.67685276386
    },
    {
        "id": "c11312",
        "legs": 4,
        "total_height": 61.67935844569783,
        "radius_bottom": 19.468142819332982,
        "radius_top": 9.203634873877972,
        "n_layers": 4,
        "layer_heights": [
            6.543736277263741,
            56.230131741970254
        ],
        "connection_types": [
            "X",
            "NONE",
            "X"
        ],
        "Cost": 640.4089604411054,
        "plausibility (FAMD GMM)": 5.470114743208023,
        "plausibility (FAMD Mahalanobis)": 0.1160837013198284,
        "plausibility (SVM)": -0.7672646773084941,
        "plausibility (One Class SVM) gamma=scale nu=0.5": 0.4207458647744815,
        "plausibility (FAMD One Class SVM) gamma=scale nu=0.5": -0.2832690209788691,
        "wave": 248237.15836986652,
        "combined": 32191228.858691804,
        "compression": 31586348.12319406,
        "tipover": 1055808.4465063303,
        "torque": 482544.7108351432
    },
    {
        "id": "c11549",
        "legs": 4,
        "total_height": 78.8120885943492,
        "radius_bottom": 16.08610037190744,
        "radius_top": 9.203634873877972,
        "n_layers": 4,
        "layer_heights": [
            16.172889027369262,
            17.544416393260803
        ],
        "connection_types": [
            "NONE",
            "NONE",
            "NONE"
        ],
        "Cost": 368.5117498754195,
        "plausibility (FAMD GMM)": 2.9444972681659274,
        "plausibility (FAMD Mahalanobis)": 1.0583575182156382,
        "plausibility (SVM)": 1.2533743261932764,
        "plausibility (One Class SVM) gamma=scale nu=0.5": 7.010003404223232,
        "plausibility (FAMD One Class SVM) gamma=scale nu=0.5": -0.25427603628146755,
        "wave": 1687313.9945775282,
        "combined": 34239660.52857029,
        "compression": 27956737.118346207,
        "tipover": 5962887.313065431,
        "torque": 1784609.2860109431
    },
    {
        "id": "c11618",
        "legs": 4,
        "total_height": 61.67935844569783,
        "radius_bottom": 16.719480091877646,
        "radius_top": 10.372317292300867,
        "n_layers": 4,
        "layer_heights": [
            15.84353493023512,
            40.71398998887875
        ],
        "connection_types": [
            "X",
            "X",
            "X"
        ],
        "Cost": 992.6558721164561,
        "plausibility (FAMD GMM)": 7.118013831185072,
        "plausibility (FAMD Mahalanobis)": 0.21511331153148439,
        "plausibility (SVM)": -1.0571288808394192,
        "plausibility (One Class SVM) gamma=scale nu=0.5": -2.4069968440638903,
        "plausibility (FAMD One Class SVM) gamma=scale nu=0.5": -0.23304932116366217,
        "wave": 102643.0647643204,
        "combined": 31119408.502682988,
        "compression": 31360330.930860978,
        "tipover": 481455.22437819256,
        "torque": 88541.34810740991
    },
    {
        "id": "c11743",
        "legs": 3,
        "total_height": 36.919118517575356,
        "radius_bottom": 16.719480091877646,
        "radius_top": 8.213346913836146,
        "n_layers": 4,
        "layer_heights": [
            6.557980820588057,
            15.84353493023512
        ],
        "connection_types": [
            "NONE",
            "NONE",
            "NONE"
        ],
        "Cost": 156.33685632250976,
        "plausibility (FAMD GMM)": 4.75509082812981,
        "plausibility (FAMD Mahalanobis)": 0.654231969295529,
        "plausibility (SVM)": 0.2221146206904856,
        "plausibility (One Class SVM) gamma=scale nu=0.5": 7.297670803408414,
        "plausibility (FAMD One Class SVM) gamma=scale nu=0.5": 0.13113548327573632,
        "wave": 1157817.53699811,
        "combined": 48496766.64237285,
        "compression": 45141318.2311659,
        "tipover": 3472531.4409719356,
        "torque": 2266222.701805681
    },
    {
        "id": "c10671",
        "legs": 4,
        "total_height": 78.8120885943492,
        "radius_bottom": 14.21440039438904,
        "radius_top": 9.203634873877972,
        "n_layers": 3,
        "layer_heights": [
            33.09505061798112
        ],
        "connection_types": [
            "K",
            "K"
        ],
        "Cost": 1160.3910136286026,
        "plausibility (FAMD GMM)": 3.935614919281527,
        "plausibility (FAMD Mahalanobis)": 0.5178880763644049,
        "plausibility (SVM)": 1.2769155811572497,
        "plausibility (One Class SVM) gamma=scale nu=0.5": 9.841288394117061,
        "plausibility (FAMD One Class SVM) gamma=scale nu=0.5": 0.7432629358229867,
        "wave": 125323.89488464402,
        "combined": 18956211.79760916,
        "compression": 19169792.535155073,
        "tipover": 512814.4741804388,
        "torque": 135949.07615124402
    },
    {
        "id": "c11536",
        "legs": 4,
        "total_height": 69.59776304183762,
        "radius_bottom": 16.08610037190744,
        "radius_top": 10.372317292300867,
        "n_layers": 4,
        "layer_heights": [
            6.543736277263741,
            7.63757538386245
        ],
        "connection_types": [
            "NONE",
            "NONE",
            "NONE"
        ],
        "Cost": 338.0023352646726,
        "plausibility (FAMD GMM)": 2.643829656592465,
        "plausibility (FAMD Mahalanobis)": 1.3517456942445483,
        "plausibility (SVM)": 1.275648151492684,
        "plausibility (One Class SVM) gamma=scale nu=0.5": 6.217638871138385,
        "plausibility (FAMD One Class SVM) gamma=scale nu=0.5": 0.4926699992641037,
        "wave": 1610579.552646636,
        "combined": 34216970.310542844,
        "compression": 28097771.41344025,
        "tipover": 5790274.7210266115,
        "torque": 1856197.572490041
    },
    {
        "id": "m2200",
        "legs": 4,
        "total_height": 78.8120885943492,
        "radius_bottom": 25.262493553913206,
        "radius_top": 9.203634873877972,
        "n_layers": 4,
        "layer_heights": [
            16.172889027369262,
            45.43344011499657
        ],
        "connection_types": [
            "X",
            "X",
            "X"
        ],
        "Cost": 1295.869171059388,
        "plausibility (FAMD GMM)": 7.053279264780115,
        "plausibility (FAMD Mahalanobis)": 1.0112526328669738,
        "plausibility (SVM)": -1.7592748900216626,
        "plausibility (One Class SVM) gamma=scale nu=0.5": 1.372476259511373,
        "plausibility (FAMD One Class SVM) gamma=scale nu=0.5": 0.11977769123303972,
        "wave": 88433.52540125076,
        "combined": 34512377.35496979,
        "compression": 34152491.67839772,
        "tipover": 418644.73024558445,
        "torque": 58287.92907221884
    },
    {
        "id": "m2320",
        "legs": 4,
        "total_height": 92.22061323184838,
        "radius_bottom": 20.64363716913241,
        "radius_top": 10.035792439640886,
        "n_layers": 4,
        "layer_heights": [
            19.834631995301123,
            56.53106720121572
        ],
        "connection_types": [
            "K",
            "K",
            "K"
        ],
        "Cost": 1516.060865457881,
        "plausibility (FAMD GMM)": 6.426743124525387,
        "plausibility (FAMD Mahalanobis)": 0.9428051901555201,
        "plausibility (SVM)": 1.2067074821555885,
        "plausibility (One Class SVM) gamma=scale nu=0.5": 8.490162015942268,
        "plausibility (FAMD One Class SVM) gamma=scale nu=0.5": 0.028795502778329762,
        "wave": 73373.33235992868,
        "combined": 22577170.338058166,
        "compression": 22575094.48756226,
        "tipover": 435630.48727414664,
        "torque": 90053.66165822683
    },
    {
        "id": "c10158",
        "legs": 4,
        "total_height": 61.67935844569783,
        "radius_bottom": 22.346988342521588,
        "radius_top": 9.203634873877972,
        "n_layers": 4,
        "layer_heights": [
            6.543736277263741,
            15.84353493023512
        ],
        "connection_types": [
            "NONE",
            "NONE",
            "NONE"
        ],
        "Cost": 304.32034737720136,
        "plausibility (FAMD GMM)": 3.576213706882769,
        "plausibility (FAMD Mahalanobis)": 1.1504907124649597,
        "plausibility (SVM)": 0.38029029208594034,
        "plausibility (One Class SVM) gamma=scale nu=0.5": 5.383546050858147,
        "plausibility (FAMD One Class SVM) gamma=scale nu=0.5": 0.43361469490869275,
        "wave": 1322552.4756162446,
        "combined": 36662403.84670825,
        "compression": 32976850.453826565,
        "tipover": 3560176.243376126,
        "torque": 1775363.6652631415
    },
    {
        "id": "c11310",
        "legs": 4,
        "total_height": 18.708731431281286,
        "radius_bottom": 16.719480091877646,
        "radius_top": 6.95772737152425,
        "n_layers": 4,
        "layer_heights": [
            9.661310646468777,
            13.017575937129056
        ],
        "connection_types": [
            "NONE",
            "X",
            "NONE"
        ],
        "Cost": 249.29442004564342,
        "plausibility (FAMD GMM)": 3.3093506124565653,
        "plausibility (FAMD Mahalanobis)": 1.2449508638080715,
        "plausibility (SVM)": -0.8936294808434204,
        "plausibility (One Class SVM) gamma=scale nu=0.5": 6.7772528355999775,
        "plausibility (FAMD One Class SVM) gamma=scale nu=0.5": 2.217640513753027,
        "wave": 371665.2700065014,
        "combined": 55804792.68462962,
        "compression": 55481256.039206944,
        "tipover": 823982.4327691006,
        "torque": 744720.8658775543
    },
    {
        "id": "c11182",
        "legs": 4,
        "total_height": 92.22061323184838,
        "radius_bottom": 27.848412247942864,
        "radius_top": 10.035792439640886,
        "n_layers": 4,
        "layer_heights": [
            15.84353493023512,
            19.834631995301123
        ],
        "connection_types": [
            "X",
            "X",
            "X"
        ],
        "Cost": 1649.8970043881243,
        "plausibility (FAMD GMM)": 6.449890551957912,
        "plausibility (FAMD Mahalanobis)": 1.9181276680454937,
        "plausibility (SVM)": -1.69458400909348,
        "plausibility (One Class SVM) gamma=scale nu=0.5": 6.015814760160152,
        "plausibility (FAMD One Class SVM) gamma=scale nu=0.5": 4.88778076000677,
        "wave": 192258.68861073305,
        "combined": 35277622.39958935,
        "compression": 34871521.327408224,
        "tipover": 426725.6659492683,
        "torque": 53733.06326004619
    },
    {
        "id": "c9159",
        "legs": 3,
        "total_height": 53.77532586162992,
        "radius_bottom": 19.468142819332982,
        "radius_top": 8.213346913836146,
        "n_layers": 4,
        "layer_heights": [
            15.84353493023512,
            22.674884523459635
        ],
        "connection_types": [
            "NONE",
            "NONE",
            "NONE"
        ],
        "Cost": 207.49923590599283,
        "plausibility (FAMD GMM)": 5.770790727336457,
        "plausibility (FAMD Mahalanobis)": 0.404754875679384,
        "plausibility (SVM)": 0.2565623557638852,
        "plausibility (One Class SVM) gamma=scale nu=0.5": 5.613848490231264,
        "plausibility (FAMD One Class SVM) gamma=scale nu=0.5": -0.3196863839695485,
        "wave": 1425402.757158666,
        "combined": 47682832.00841625,
        "compression": 43557067.83103268,
        "tipover": 4350071.934664876,
        "torque": 2373139.493395263
    },
    {
        "id": "c11562",
        "legs": 3,
        "total_height": 18.708731431281286,
        "radius_bottom": 22.441147571929765,
        "radius_top": 9.203634873877972,
        "n_layers": 4,
        "layer_heights": [
            10.197290965625525,
            13.017575937129056
        ],
        "connection_types": [
            "NONE",
            "NONE",
            "NONE"
        ],
        "Cost": 116.57838305738713,
        "plausibility (FAMD GMM)": 1.6516031352857672,
        "plausibility (FAMD Mahalanobis)": 0.769427479560106,
        "plausibility (SVM)": -0.5250781800807593,
        "plausibility (One Class SVM) gamma=scale nu=0.5": 10.431815856870177,
        "plausibility (FAMD One Class SVM) gamma=scale nu=0.5": 0.3865401032434157,
        "wave": 806029.162126725,
        "combined": 95102328.62871312,
        "compression": 94076562.53212912,
        "tipover": 1867780.6201050484,
        "torque": 1321378.8982882868
    },
    {
        "id": "m2004",
        "legs": 4,
        "total_height": 61.67935844569783,
        "radius_bottom": 18.691659977845262,
        "radius_top": 9.203634873877972,
        "n_layers": 4,
        "layer_heights": [
            10.197290965625525,
            56.230131741970254
        ],
        "connection_types": [
            "X",
            "NONE",
            "NONE"
        ],
        "Cost": 520.2691898503437,
        "plausibility (FAMD GMM)": 4.250904916529354,
        "plausibility (FAMD Mahalanobis)": 0.033884162642881334,
        "plausibility (SVM)": -0.06920861001073808,
        "plausibility (One Class SVM) gamma=scale nu=0.5": 1.8467224018794397,
        "plausibility (FAMD One Class SVM) gamma=scale nu=0.5": -0.1599291374207752,
        "wave": 396554.6276274071,
        "combined": 32830575.47891357,
        "compression": 32078924.72270311,
        "tipover": 1480141.2025741914,
        "torque": 583530.6595400121
    },
    {
        "id": "c11580",
        "legs": 3,
        "total_height": 19.44671201273131,
        "radius_bottom": 22.346988342521588,
        "radius_top": 8.213346913836146,
        "n_layers": 4,
        "layer_heights": [
            6.543736277263741,
            15.84353493023512
        ],
        "connection_types": [
            "NONE",
            "NONE",
            "NONE"
        ],
        "Cost": 114.79860288517435,
        "plausibility (FAMD GMM)": 1.6576480141540881,
        "plausibility (FAMD Mahalanobis)": 0.670187016060094,
        "plausibility (SVM)": -0.6252573281070872,
        "plausibility (One Class SVM) gamma=scale nu=0.5": 10.442092947806529,
        "plausibility (FAMD One Class SVM) gamma=scale nu=0.5": 0.5893024000317926,
        "wave": 785583.0946971728,
        "combined": 97325639.0951572,
        "compression": 96409842.60650392,
        "tipover": 1784152.585696182,
        "torque": 1381850.3719057653
    },
    {
        "id": "c6365",
        "legs": 4,
        "total_height": 18.708731431281286,
        "radius_bottom": 27.848412247942864,
        "radius_top": 8.213346913836146,
        "n_layers": 4,
        "layer_heights": [
            13.017575937129056,
            15.84353493023512
        ],
        "connection_types": [
            "X",
            "X",
            "X"
        ],
        "Cost": 685.8281591818009,
        "plausibility (FAMD GMM)": 5.850729179661503,
        "plausibility (FAMD Mahalanobis)": 1.1330798177461652,
        "plausibility (SVM)": -3.1802902533361865,
        "plausibility (One Class SVM) gamma=scale nu=0.5": 8.944903297254283,
        "plausibility (FAMD One Class SVM) gamma=scale nu=0.5": 0.7318255280702441,
        "wave": 169746.5565343959,
        "combined": 107759035.6398354,
        "compression": 107473323.7471168,
        "tipover": 291454.64968673675,
        "torque": 53382.59000442227
    },
    {
        "id": "c11657",
        "legs": 4,
        "total_height": 92.22061323184838,
        "radius_bottom": 27.848412247942864,
        "radius_top": 9.203634873877972,
        "n_layers": 4,
        "layer_heights": [
            15.84353493023512,
            19.834631995301123
        ],
        "connection_types": [
            "K",
            "X",
            "K"
        ],
        "Cost": 1773.5239497085402,
        "plausibility (FAMD GMM)": 6.126347573959279,
        "plausibility (FAMD Mahalanobis)": 1.8516001122476242,
        "plausibility (SVM)": -0.4895100170306441,
        "plausibility (One Class SVM) gamma=scale nu=0.5": 9.738675694561227,
        "plausibility (FAMD One Class SVM) gamma=scale nu=0.5": 4.483511145776825,
        "wave": 90654.5197142529,
        "combined": 33598275.12859564,
        "compression": 34883209.91360303,
        "tipover": 399922.2054215778,
        "torque": 71504.6780853915
    },
    {
        "id": "c11475",
        "legs": 4,
        "total_height": 92.22061323184838,
        "radius_bottom": 25.262493553913206,
        "radius_top": 10.035792439640886,
        "n_layers": 4,
        "layer_heights": [
            15.84353493023512,
            19.834631995301123
        ],
        "connection_types": [
            "X",
            "X",
            "X"
        ],
        "Cost": 1595.2450006072208,
        "plausibility (FAMD GMM)": 5.5901964221944995,
        "plausibility (FAMD Mahalanobis)": 1.7618054150688631,
        "plausibility (SVM)": -1.4219488077369014,
        "plausibility (One Class SVM) gamma=scale nu=0.5": 3.983564239185002,
        "plausibility (FAMD One Class SVM) gamma=scale nu=0.5": 3.955203610756625,
        "wave": 192224.7283337992,
        "combined": 33926886.615400456,
        "compression": 33315234.261350285,
        "tipover": 455981.0866679569,
        "torque": 59397.726509699176
    },
    {
        "id": "c11645",
        "legs": 3,
        "total_height": 18.708731431281286,
        "radius_bottom": 16.719480091877646,
        "radius_top": 8.682735991085853,
        "n_layers": 4,
        "layer_heights": [
            7.839348015471635,
            10.197290965625525
        ],
        "connection_types": [
            "NONE",
            "NONE",
            "Z"
        ],
        "Cost": 166.74167370408296,
        "plausibility (FAMD GMM)": 5.293022803476873,
        "plausibility (FAMD Mahalanobis)": 0.8516100854427808,
        "plausibility (SVM)": -0.004317137497328982,
        "plausibility (One Class SVM) gamma=scale nu=0.5": 10.56622258457736,
        "plausibility (FAMD One Class SVM) gamma=scale nu=0.5": 1.750854361709509,
        "wave": 663737.4033979718,
        "combined": 65308049.562636875,
        "compression": 64292610.11517115,
        "tipover": 2123758.778173402,
        "torque": 1379248.9493294267
    },
    {
        "id": "m2220",
        "legs": 4,
        "total_height": 54.34289691123913,
        "radius_bottom": 19.468142819332982,
        "radius_top": 8.213346913836146,
        "n_layers": 4,
        "layer_heights": [
            6.543736277263741,
            50.62808332768375
        ],
        "connection_types": [
            "X",
            "NONE",
            "X"
        ],
        "Cost": 589.3285425023078,
        "plausibility (FAMD GMM)": 4.687343828718911,
        "plausibility (FAMD Mahalanobis)": 0.16494860556288837,
        "plausibility (SVM)": -1.0338992065366504,
        "plausibility (One Class SVM) gamma=scale nu=0.5": 0.7690361479166228,
        "plausibility (FAMD One Class SVM) gamma=scale nu=0.5": 0.05296720287091361,
        "wave": 216945.57387616072,
        "combined": 33857757.17745102,
        "compression": 33293020.435078386,
        "tipover": 886854.6017364463,
        "torque": 453559.6252989153
    },
    {
        "id": "c10558",
        "legs": 3,
        "total_height": 32.60832969128558,
        "radius_bottom": 14.21440039438904,
        "radius_top": 9.873465670969402,
        "n_layers": 4,
        "layer_heights": [
            6.543736277263741,
            15.84353493023512
        ],
        "connection_types": [
            "NONE",
            "NONE",
            "NONE"
        ],
        "Cost": 149.9920354635098,
        "plausibility (FAMD GMM)": 5.706497371091086,
        "plausibility (FAMD Mahalanobis)": 0.6836993894316296,
        "plausibility (SVM)": 0.5852787971493236,
        "plausibility (One Class SVM) gamma=scale nu=0.5": 8.515622892963155,
        "plausibility (FAMD One Class SVM) gamma=scale nu=0.5": 0.6869395371169098,
        "wave": 1188129.708845443,
        "combined": 44135335.565214634,
        "compression": 40200113.92068038,
        "tipover": 3963808.381107316,
        "torque": 2280561.4463454722
    },
    {
        "id": "m2296",
        "legs": 4,
        "total_height": 61.67935844569783,
        "radius_bottom": 19.468142819332982,
        "radius_top": 9.203634873877972,
        "n_layers": 4,
        "layer_heights": [
            17.544416393260803,
            22.674884523459635
        ],
        "connection_types": [
            "NONE",
            "X",
            "ZH"
        ],
        "Cost": 750.1313579494071,
        "plausibility (FAMD GMM)": 5.013997567679678,
        "plausibility (FAMD Mahalanobis)": 0.5982668651683383,
        "plausibility (SVM)": 0.0004144681921425253,
        "plausibility (One Class SVM) gamma=scale nu=0.5": 2.6935317926801616,
        "plausibility (FAMD One Class SVM) gamma=scale nu=0.5": -0.4638804476697498,
        "wave": 436919.9301876031,
        "combined": 32142953.59571649,
        "compression": 30708295.07285912,
        "tipover": 1417119.1709670378,
        "torque": 938426.7306009579
    },
    {
        "id": "m2280",
        "legs": 4,
        "total_height": 18.708731431281286,
        "radius_bottom": 19.468142819332982,
        "radius_top": 9.203634873877972,
        "n_layers": 4,
        "layer_heights": [
            6.543736277263741,
            16.172889027369262
        ],
        "connection_types": [
            "NONE",
            "IZ",
            "NONE"
        ],
        "Cost": 222.93973397389937,
        "plausibility (FAMD GMM)": 1.9680009980926905,
        "plausibility (FAMD Mahalanobis)": 0.855304168686395,
        "plausibility (SVM)": 0.0024346163363966333,
        "plausibility (One Class SVM) gamma=scale nu=0.5": 8.409779168282554,
        "plausibility (FAMD One Class SVM) gamma=scale nu=0.5": 0.9273801453851043,
        "wave": 547706.6340815768,
        "combined": 57559976.9071654,
        "compression": 57370898.078148395,
        "tipover": 1282892.091676245,
        "torque": 569839.5299285947
    },
    {
        "id": "c10890",
        "legs": 4,
        "total_height": 92.22061323184838,
        "radius_bottom": 13.645671683805878,
        "radius_top": 10.035792439640886,
        "n_layers": 4,
        "layer_heights": [
            15.84353493023512,
            56.53106720121572
        ],
        "connection_types": [
            "NONE",
            "NONE",
            "NONE"
        ],
        "Cost": 425.9359697409397,
        "plausibility (FAMD GMM)": 4.516135481547877,
        "plausibility (FAMD Mahalanobis)": 0.6759031946534902,
        "plausibility (SVM)": 1.7903115653209576,
        "plausibility (One Class SVM) gamma=scale nu=0.5": 10.045715207298938,
        "plausibility (FAMD One Class SVM) gamma=scale nu=0.5": -0.4716323510269884,
        "wave": 2001839.0113384046,
        "combined": 35768976.44209013,
        "compression": 27138854.5695458,
        "tipover": 8501271.29487391,
        "torque": 1712771.807958341
    },
    {
        "id": "c11539",
        "legs": 3,
        "total_height": 36.919118517575356,
        "radius_bottom": 19.154759644696405,
        "radius_top": 8.213346913836146,
        "n_layers": 4,
        "layer_heights": [
            6.557980820588057,
            19.877808441112457
        ],
        "connection_types": [
            "NONE",
            "NONE",
            "X"
        ],
        "Cost": 310.3096590979852,
        "plausibility (FAMD GMM)": 6.140075031658041,
        "plausibility (FAMD Mahalanobis)": 0.4404368355842074,
        "plausibility (SVM)": -0.6219678813268152,
        "plausibility (One Class SVM) gamma=scale nu=0.5": 6.557515278714396,
        "plausibility (FAMD One Class SVM) gamma=scale nu=0.5": 0.11728227629591004,
        "wave": 725862.0741338149,
        "combined": 60061537.76914939,
        "compression": 58384287.33053402,
        "tipover": 2196349.734686051,
        "torque": 1589421.2023596768
    },
    {
        "id": "c8659",
        "legs": 4,
        "total_height": 61.67935844569783,
        "radius_bottom": 14.547691928204214,
        "radius_top": 12.591484647035323,
        "n_layers": 3,
        "layer_heights": [
            58.66478978662678
        ],
        "connection_types": [
            "NONE",
            "K"
        ],
        "Cost": 465.0408236566857,
        "plausibility (FAMD GMM)": 5.256655945493516,
        "plausibility (FAMD Mahalanobis)": 1.2999099811712382,
        "plausibility (SVM)": 1.5164334413833083,
        "plausibility (One Class SVM) gamma=scale nu=0.5": 9.556837414388296,
        "plausibility (FAMD One Class SVM) gamma=scale nu=0.5": 0.6327484865855713,
        "wave": 1395314.4543426125,
        "combined": 33366628.424727507,
        "compression": 26491333.948087268,
        "tipover": 6221223.317573767,
        "torque": 1932430.3780018298
    },
    {
        "id": "c11597",
        "legs": 4,
        "total_height": 18.708731431281286,
        "radius_bottom": 27.848412247942864,
        "radius_top": 9.203634873877972,
        "n_layers": 4,
        "layer_heights": [
            13.017575937129056,
            15.84353493023512
        ],
        "connection_types": [
            "X",
            "X",
            "X"
        ],
        "Cost": 709.2795380021561,
        "plausibility (FAMD GMM)": 6.025516243228908,
        "plausibility (FAMD Mahalanobis)": 1.1100129127329574,
        "plausibility (SVM)": -3.043816046745993,
        "plausibility (One Class SVM) gamma=scale nu=0.5": 8.708909547755566,
        "plausibility (FAMD One Class SVM) gamma=scale nu=0.5": 0.8323443464021967,
        "wave": 168740.9712989894,
        "combined": 102761813.5084624,
        "compression": 102503740.39450271,
        "tipover": 287506.3232855749,
        "torque": 52778.90670167915
    },
    {
        "id": "c11005",
        "legs": 4,
        "total_height": 82.52687027810286,
        "radius_bottom": 19.468142819332982,
        "radius_top": 8.213346913836146,
        "n_layers": 4,
        "layer_heights": [
            45.43344011499657,
            50.62808332768375
        ],
        "connection_types": [
            "K",
            "K",
            "K"
        ],
        "Cost": 1351.6702687826316,
        "plausibility (FAMD GMM)": 2.0534291272929073,
        "plausibility (FAMD Mahalanobis)": 0.23032307898859297,
        "plausibility (SVM)": 0.8786608950819734,
        "plausibility (One Class SVM) gamma=scale nu=0.5": 7.409299583861694,
        "plausibility (FAMD One Class SVM) gamma=scale nu=0.5": -0.4418972346456709,
        "wave": 82220.30495991246,
        "combined": 17768615.036689438,
        "compression": 17284748.004688684,
        "tipover": 438740.4976357598,
        "torque": 99549.05059642113
    },
    {
        "id": "c11703",
        "legs": 4,
        "total_height": 32.60832969128558,
        "radius_bottom": 13.645671683805878,
        "radius_top": 9.203634873877972,
        "n_layers": 4,
        "layer_heights": [
            2.9329403282829567,
            6.543736277263741
        ],
        "connection_types": [
            "NONE",
            "NONE",
            "NONE"
        ],
        "Cost": 183.7016007505813,
        "plausibility (FAMD GMM)": 2.3314792889101352,
        "plausibility (FAMD Mahalanobis)": 1.0614688172355873,
        "plausibility (SVM)": 0.6556459097095435,
        "plausibility (One Class SVM) gamma=scale nu=0.5": 7.48428614695151,
        "plausibility (FAMD One Class SVM) gamma=scale nu=0.5": -0.7638607795597743,
        "wave": 973308.9698260423,
        "combined": 33283431.870889388,
        "compression": 30029850.26950936,
        "tipover": 2875447.381051743,
        "torque": 1740768.2304274621
    },
    {
        "id": "c11507",
        "legs": 3,
        "total_height": 54.34289691123913,
        "radius_bottom": 19.154759644696405,
        "radius_top": 8.682735991085853,
        "n_layers": 4,
        "layer_heights": [
            6.543736277263741,
            50.62808332768375
        ],
        "connection_types": [
            "NONE",
            "NONE",
            "X"
        ],
        "Cost": 307.7297558052977,
        "plausibility (FAMD GMM)": 4.657047081756042,
        "plausibility (FAMD Mahalanobis)": 0.14514962850363097,
        "plausibility (SVM)": -0.2574670781648698,
        "plausibility (One Class SVM) gamma=scale nu=0.5": 4.521528447426897,
        "plausibility (FAMD One Class SVM) gamma=scale nu=0.5": 0.018254019214554162,
        "wave": 1247062.0659150647,
        "combined": 46514521.860621154,
        "compression": 42148455.634136036,
        "tipover": 4586549.701930034,
        "torque": 2388460.218205071
    },
    {
        "id": "c11708",
        "legs": 4,
        "total_height": 69.59776304183762,
        "radius_bottom": 13.645671683805878,
        "radius_top": 8.213346913836146,
        "n_layers": 3,
        "layer_heights": [
            56.53106720121572
        ],
        "connection_types": [
            "K",
            "K"
        ],
        "Cost": 1025.5998758150029,
        "plausibility (FAMD GMM)": 3.914722807583321,
        "plausibility (FAMD Mahalanobis)": 1.2875480773835846,
        "plausibility (SVM)": 0.9921381890332932,
        "plausibility (One Class SVM) gamma=scale nu=0.5": 9.290081126435759,
        "plausibility (FAMD One Class SVM) gamma=scale nu=0.5": 1.1568809323632898,
        "wave": 503996.29603430873,
        "combined": 16675175.806539023,
        "compression": 16013159.34120792,
        "tipover": 699693.9197367787,
        "torque": 303304.4591363021
    },
    {
        "id": "c11365",
        "legs": 3,
        "total_height": 54.34289691123913,
        "radius_bottom": 19.154759644696405,
        "radius_top": 8.682735991085853,
        "n_layers": 4,
        "layer_heights": [
            6.543736277263741,
            50.62808332768375
        ],
        "connection_types": [
            "NONE",
            "NONE",
            "NONE"
        ],
        "Cost": 211.14490016318592,
        "plausibility (FAMD GMM)": 4.657047081756042,
        "plausibility (FAMD Mahalanobis)": 0.14514962850363097,
        "plausibility (SVM)": 0.37275590645047396,
        "plausibility (One Class SVM) gamma=scale nu=0.5": 5.379941591462483,
        "plausibility (FAMD One Class SVM) gamma=scale nu=0.5": 0.018254019214554162,
        "wave": 1471688.529800084,
        "combined": 46997308.904327735,
        "compression": 42559554.11056424,
        "tipover": 4655894.1915889215,
        "torque": 2393035.9852122846
    },
    {
        "id": "m2337",
        "legs": 4,
        "total_height": 92.22061323184838,
        "radius_bottom": 19.154759644696405,
        "radius_top": 8.213346913836146,
        "n_layers": 4,
        "layer_heights": [
            14.71134409405373,
            15.84353493023512
        ],
        "connection_types": [
            "NONE",
            "NONE",
            "NONE"
        ],
        "Cost": 417.93135021037364,
        "plausibility (FAMD GMM)": 3.408000435240481,
        "plausibility (FAMD Mahalanobis)": 1.4189330339909103,
        "plausibility (SVM)": 1.0524855814070073,
        "plausibility (One Class SVM) gamma=scale nu=0.5": 8.862316945319535,
        "plausibility (FAMD One Class SVM) gamma=scale nu=0.5": 1.510524621683306,
        "wave": 1743771.3864438368,
        "combined": 34358588.27411541,
        "compression": 28676772.493134275,
        "tipover": 5429336.871890179,
        "torque": 1711960.0459632177
    },
    {
        "id": "m2341",
        "legs": 4,
        "total_height": 62.88219651477844,
        "radius_bottom": 13.32949964427397,
        "radius_top": 10.372317292300867,
        "n_layers": 4,
        "layer_heights": [
            5.148398030254616,
            7.601203745753133
        ],
        "connection_types": [
            "NONE",
            "NONE",
            "NONE"
        ],
        "Cost": 310.4814564331184,
        "plausibility (FAMD GMM)": 2.1397114101975165,
        "plausibility (FAMD Mahalanobis)": 1.2657197756052834,
        "plausibility (SVM)": 1.3876518245256144,
        "plausibility (One Class SVM) gamma=scale nu=0.5": 7.165947920592629,
        "plausibility (FAMD One Class SVM) gamma=scale nu=0.5": -0.511044009488737,
        "wave": 1567987.3212190731,
        "combined": 34000314.01244824,
        "compression": 27579160.519951236,
        "tipover": 6053596.991490433,
        "torque": 1886105.225171448
    },
    {
        "id": "c11247",
        "legs": 4,
        "total_height": 79.9247665214869,
        "radius_bottom": 16.719480091877646,
        "radius_top": 10.372317292300867,
        "n_layers": 4,
        "layer_heights": [
            3.8392923038127216,
            9.661310646468777
        ],
        "connection_types": [
            "X",
            "X",
            "NONE"
        ],
        "Cost": 758.2662796539696,
        "plausibility (FAMD GMM)": 3.1497916498511978,
        "plausibility (FAMD Mahalanobis)": 1.5473652126421222,
        "plausibility (SVM)": -0.09277248354566359,
        "plausibility (One Class SVM) gamma=scale nu=0.5": 2.3734574939189805,
        "plausibility (FAMD One Class SVM) gamma=scale nu=0.5": 1.8166936315200601,
        "wave": 318081.5575315951,
        "combined": 28976605.5722723,
        "compression": 28294485.822125144,
        "tipover": 645027.1635758211,
        "torque": 316710.98605738784
    },
    {
        "id": "c11434",
        "legs": 3,
        "total_height": 36.83892676380137,
        "radius_bottom": 22.441147571929765,
        "radius_top": 8.682735991085853,
        "n_layers": 4,
        "layer_heights": [
            7.63757538386245,
            13.017575937129056
        ],
        "connection_types": [
            "NONE",
            "NONE",
            "NONE"
        ],
        "Cost": 163.08971369943296,
        "plausibility (FAMD GMM)": 5.003975738172165,
        "plausibility (FAMD Mahalanobis)": 0.527812259879929,
        "plausibility (SVM)": -0.24697626460132005,
        "plausibility (One Class SVM) gamma=scale nu=0.5": 7.817221910254977,
        "plausibility (FAMD One Class SVM) gamma=scale nu=0.5": -0.45406756388893044,
        "wave": 1096651.7013256773,
        "combined": 59966281.71783575,
        "compression": 57462266.7163402,
        "tipover": 2917813.8895291295,
        "torque": 2000668.3576635495
    },
    {
        "id": "m2267",
        "legs": 3,
        "total_height": 18.708731431281286,
        "radius_bottom": 19.154759644696405,
        "radius_top": 8.213346913836146,
        "n_layers": 4,
        "layer_heights": [
            8.148577245037343,
            13.017575937129056
        ],
        "connection_types": [
            "NONE",
            "X",
            "NONE"
        ],
        "Cost": 245.83379153142482,
        "plausibility (FAMD GMM)": 2.504910759095479,
        "plausibility (FAMD Mahalanobis)": 0.8745782392089021,
        "plausibility (SVM)": -1.0275210976597058,
        "plausibility (One Class SVM) gamma=scale nu=0.5": 8.226504684524357,
        "plausibility (FAMD One Class SVM) gamma=scale nu=0.5": 1.2513142289567138,
        "wave": 457016.7406588089,
        "combined": 81022834.17126596,
        "compression": 80871541.45272353,
        "tipover": 1243185.0259516607,
        "torque": 818723.7981847117
    },
    {
        "id": "c11727",
        "legs": 4,
        "total_height": 78.8120885943492,
        "radius_bottom": 19.468142819332982,
        "radius_top": 9.203634873877972,
        "n_layers": 4,
        "layer_heights": [
            7.839348015471635,
            33.09505061798112
        ],
        "connection_types": [
            "NONE",
            "K",
            "NONE"
        ],
        "Cost": 694.602017863424,
        "plausibility (FAMD GMM)": 3.780241129474561,
        "plausibility (FAMD Mahalanobis)": 1.05217067875649,
        "plausibility (SVM)": 1.0831193220364477,
        "plausibility (One Class SVM) gamma=scale nu=0.5": 6.211020110159437,
        "plausibility (FAMD One Class SVM) gamma=scale nu=0.5": 0.16112414379695217,
        "wave": 422858.7490112389,
        "combined": 30124504.17536105,
        "compression": 29722639.220911555,
        "tipover": 617492.3581273885,
        "torque": 375852.1184361727
    },
    {
        "id": "m2251",
        "legs": 4,
        "total_height": 61.67935844569783,
        "radius_bottom": 26.789402795743477,
        "radius_top": 9.203634873877972,
        "n_layers": 4,
        "layer_heights": [
            10.197290965625525,
            56.230131741970254
        ],
        "connection_types": [
            "NONE",
            "NONE",
            "NONE"
        ],
        "Cost": 308.6131091907709,
        "plausibility (FAMD GMM)": 1.7838244787656516,
        "plausibility (FAMD Mahalanobis)": 0.6115573869340648,
        "plausibility (SVM)": -0.10484552825923776,
        "plausibility (One Class SVM) gamma=scale nu=0.5": 7.781343656868179,
        "plausibility (FAMD One Class SVM) gamma=scale nu=0.5": -0.612622410206443,
        "wave": 1280427.2459807352,
        "combined": 40035596.87505594,
        "compression": 37093726.39475185,
        "tipover": 3060525.9282099796,
        "torque": 1698572.9965699548
    },
    {
        "id": "c11387",
        "legs": 3,
        "total_height": 18.708731431281286,
        "radius_bottom": 19.468142819332982,
        "radius_top": 10.035792439640886,
        "n_layers": 4,
        "layer_heights": [
            7.839348015471635,
            10.197290965625525
        ],
        "connection_types": [
            "Z",
            "NONE",
            "NONE"
        ],
        "Cost": 209.07476040961794,
        "plausibility (FAMD GMM)": 3.4680202151435813,
        "plausibility (FAMD Mahalanobis)": 0.5194989666746647,
        "plausibility (SVM)": -0.1065501142437788,
        "plausibility (One Class SVM) gamma=scale nu=0.5": 9.871766577407184,
        "plausibility (FAMD One Class SVM) gamma=scale nu=0.5": 0.7027688624785888,
        "wave": 741184.3842447322,
        "combined": 71850212.22987281,
        "compression": 71255468.91856602,
        "tipover": 1405007.85779583,
        "torque": 890066.320734452
    },
    {
        "id": "c11675",
        "legs": 4,
        "total_height": 61.67935844569783,
        "radius_bottom": 19.468142819332982,
        "radius_top": 9.203634873877972,
        "n_layers": 4,
        "layer_heights": [
            13.017575937129056,
            22.674884523459635
        ],
        "connection_types": [
            "X",
            "X",
            "X"
        ],
        "Cost": 1081.6444437818354,
        "plausibility (FAMD GMM)": 4.296127044494406,
        "plausibility (FAMD Mahalanobis)": 0.7230394883656633,
        "plausibility (SVM)": -1.4667351460442766,
        "plausibility (One Class SVM) gamma=scale nu=0.5": -3.0304820574629154,
        "plausibility (FAMD One Class SVM) gamma=scale nu=0.5": -0.4612742725578034,
        "wave": 112083.18134793926,
        "combined": 34425954.25772326,
        "compression": 34185631.189430326,
        "tipover": 435509.7557603079,
        "torque": 79551.4616431101
    },
    {
        "id": "m2343",
        "legs": 3,
        "total_height": 61.67935844569783,
        "radius_bottom": 19.468142819332982,
        "radius_top": 9.203634873877972,
        "n_layers": 4,
        "layer_heights": [
            32.39521774725318,
            40.71398998887875
        ],
        "connection_types": [
            "NONE",
            "NONE",
            "X"
        ],
        "Cost": 405.34250381312063,
        "plausibility (FAMD GMM)": 1.3290095966394815,
        "plausibility (FAMD Mahalanobis)": 0.24527674472063435,
        "plausibility (SVM)": -0.12271267657593432,
        "plausibility (One Class SVM) gamma=scale nu=0.5": 3.950849745352901,
        "plausibility (FAMD One Class SVM) gamma=scale nu=0.5": -0.17793382669314184,
        "wave": 1180048.7265736077,
        "combined": 48617699.62979895,
        "compression": 44769252.17676745,
        "tipover": 4120691.9026602544,
        "torque": 2335509.590110266
    },
    {
        "id": "c11497",
        "legs": 3,
        "total_height": 54.34289691123913,
        "radius_bottom": 13.645671683805878,
        "radius_top": 8.375906891368846,
        "n_layers": 4,
        "layer_heights": [
            9.661310646468777,
            18.676170579105044
        ],
        "connection_types": [
            "X",
            "NONE",
            "NONE"
        ],
        "Cost": 356.04799473468665,
        "plausibility (FAMD GMM)": 3.246238176691661,
        "plausibility (FAMD Mahalanobis)": 0.8170542892314334,
        "plausibility (SVM)": 0.015671835272323964,
        "plausibility (One Class SVM) gamma=scale nu=0.5": 5.074522486943627,
        "plausibility (FAMD One Class SVM) gamma=scale nu=0.5": -0.49580312725717945,
        "wave": 493949.7701032245,
        "combined": 40689200.54858788,
        "compression": 39907866.558596574,
        "tipover": 2569385.807571781,
        "torque": 715557.9546524332
    },
    {
        "id": "c11572",
        "legs": 3,
        "total_height": 41.79608223523681,
        "radius_bottom": 19.154759644696405,
        "radius_top": 9.203634873877972,
        "n_layers": 4,
        "layer_heights": [
            22.674884523459635,
            26.728884247510326
        ],
        "connection_types": [
            "NONE",
            "X",
            "NONE"
        ],
        "Cost": 316.8174686539291,
        "plausibility (FAMD GMM)": 1.450967790980101,
        "plausibility (FAMD Mahalanobis)": 0.5063042031751185,
        "plausibility (SVM)": -0.4946051960437692,
        "plausibility (One Class SVM) gamma=scale nu=0.5": 3.773836116338524,
        "plausibility (FAMD One Class SVM) gamma=scale nu=0.5": 0.29783988150433593,
        "wave": 786136.60802347,
        "combined": 48150561.85435073,
        "compression": 46372126.98754868,
        "tipover": 2813232.418100185,
        "torque": 1643699.567962637
    },
    {
        "id": "c11244",
        "legs": 4,
        "total_height": 82.52687027810286,
        "radius_bottom": 25.262493553913206,
        "radius_top": 9.203634873877972,
        "n_layers": 4,
        "layer_heights": [
            13.017575937129056,
            45.43344011499657
        ],
        "connection_types": [
            "X",
            "K",
            "X"
        ],
        "Cost": 1418.604095013552,
        "plausibility (FAMD GMM)": 6.3894132716685474,
        "plausibility (FAMD Mahalanobis)": 1.1591353524318633,
        "plausibility (SVM)": -0.8737461453673823,
        "plausibility (One Class SVM) gamma=scale nu=0.5": 4.718325385543073,
        "plausibility (FAMD One Class SVM) gamma=scale nu=0.5": 0.63723623538956,
        "wave": 83215.89003139992,
        "combined": 37082229.18012469,
        "compression": 37967018.050446935,
        "tipover": 434375.30025144725,
        "torque": 60600.679912570355
    },
    {
        "id": "c11742",
        "legs": 4,
        "total_height": 18.708731431281286,
        "radius_bottom": 19.154759644696405,
        "radius_top": 9.203634873877972,
        "n_layers": 4,
        "layer_heights": [
            6.543736277263741,
            18.09884705469489
        ],
        "connection_types": [
            "NONE",
            "NONE",
            "X"
        ],
        "Cost": 242.91646401672284,
        "plausibility (FAMD GMM)": 2.269472003602383,
        "plausibility (FAMD Mahalanobis)": 1.000356492521357,
        "plausibility (SVM)": -0.7189910328737503,
        "plausibility (One Class SVM) gamma=scale nu=0.5": 7.925171509320114,
        "plausibility (FAMD One Class SVM) gamma=scale nu=0.5": 0.9417970663109063,
        "wave": 628609.0023533136,
        "combined": 56765592.48469619,
        "compression": 55760816.329684444,
        "tipover": 1458510.455634151,
        "torque": 1073334.0839501668
    },
    {
        "id": "c11741",
        "legs": 3,
        "total_height": 32.60832969128558,
        "radius_bottom": 19.468142819332982,
        "radius_top": 9.873465670969402,
        "n_layers": 4,
        "layer_heights": [
            6.543736277263741,
            15.259732032633382
        ],
        "connection_types": [
            "NONE",
            "IZH",
            "IZH"
        ],
        "Cost": 494.07168723572255,
        "plausibility (FAMD GMM)": 5.93487871434477,
        "plausibility (FAMD Mahalanobis)": 0.3966431206944959,
        "plausibility (SVM)": 0.3294792806149851,
        "plausibility (One Class SVM) gamma=scale nu=0.5": 8.297067187407736,
        "plausibility (FAMD One Class SVM) gamma=scale nu=0.5": -0.13833687112609638,
        "wave": 353054.40916114236,
        "combined": 52919282.520625316,
        "compression": 53038134.86379718,
        "tipover": 1261003.3558754034,
        "torque": 730973.113057167
    },
    {
        "id": "m2250",
        "legs": 4,
        "total_height": 32.60832969128558,
        "radius_bottom": 20.994650332340566,
        "radius_top": 8.682735991085853,
        "n_layers": 4,
        "layer_heights": [
            16.172889027369262,
            19.834631995301123
        ],
        "connection_types": [
            "NONE",
            "NONE",
            "NONE"
        ],
        "Cost": 188.53785421208258,
        "plausibility (FAMD GMM)": 1.7190057485443562,
        "plausibility (FAMD Mahalanobis)": 0.4754635002513359,
        "plausibility (SVM)": -0.10633732114891847,
        "plausibility (One Class SVM) gamma=scale nu=0.5": 6.453593682149812,
        "plausibility (FAMD One Class SVM) gamma=scale nu=0.5": 0.32902205556775677,
        "wave": 871846.4017918449,
        "combined": 45155122.54741011,
        "compression": 43419401.29989478,
        "tipover": 2040425.618558978,
        "torque": 1456744.8494769498
    },
    {
        "id": "c11569",
        "legs": 4,
        "total_height": 32.60832969128558,
        "radius_bottom": 19.154759644696405,
        "radius_top": 8.213346913836146,
        "n_layers": 4,
        "layer_heights": [
            2.9329403282829567,
            8.148577245037343
        ],
        "connection_types": [
            "NONE",
            "NONE",
            "NONE"
        ],
        "Cost": 184.0418024991995,
        "plausibility (FAMD GMM)": 2.863242511891966,
        "plausibility (FAMD Mahalanobis)": 0.8588931101913853,
        "plausibility (SVM)": 0.042375733337815635,
        "plausibility (One Class SVM) gamma=scale nu=0.5": 6.5222385441518185,
        "plausibility (FAMD One Class SVM) gamma=scale nu=0.5": -0.7914631916969928,
        "wave": 868659.1230303671,
        "combined": 42275280.182981044,
        "compression": 40423412.84091169,
        "tipover": 2081315.9487432626,
        "torque": 1523557.7127644566
    },
    {
        "id": "c10748",
        "legs": 4,
        "total_height": 54.34289691123913,
        "radius_bottom": 19.468142819332982,
        "radius_top": 8.213346913836146,
        "n_layers": 4,
        "layer_heights": [
            7.839348015471635,
            50.62808332768375
        ],
        "connection_types": [
            "X",
            "X",
            "X"
        ],
        "Cost": 968.4197005897281,
        "plausibility (FAMD GMM)": 4.111938677458523,
        "plausibility (FAMD Mahalanobis)": 0.18081370674735656,
        "plausibility (SVM)": -1.730814283240297,
        "plausibility (One Class SVM) gamma=scale nu=0.5": -2.6685765343457106,
        "plausibility (FAMD One Class SVM) gamma=scale nu=0.5": 0.07241572851071076,
        "wave": 147448.605480017,
        "combined": 35743742.938889585,
        "compression": 37229138.37429742,
        "tipover": 422698.92660966626,
        "torque": 92920.25989709605
    },
    {
        "id": "c11254",
        "legs": 4,
        "total_height": 18.708731431281286,
        "radius_bottom": 27.848412247942864,
        "radius_top": 10.035792439640886,
        "n_layers": 4,
        "layer_heights": [
            7.839348015471635,
            10.197290965625525
        ],
        "connection_types": [
            "X",
            "X",
            "X"
        ],
        "Cost": 841.6156465112514,
        "plausibility (FAMD GMM)": 1.0117240166581978,
        "plausibility (FAMD Mahalanobis)": 0.2892815260048315,
        "plausibility (SVM)": -2.899946683545797,
        "plausibility (One Class SVM) gamma=scale nu=0.5": 8.632395457138875,
        "plausibility (FAMD One Class SVM) gamma=scale nu=0.5": -0.38635276474798275,
        "wave": 89983.98422427318,
        "combined": 94569409.17501801,
        "compression": 95069715.21139832,
        "tipover": 294302.2164283946,
        "torque": 61050.98687568227
    },
    {
        "id": "c11560",
        "legs": 3,
        "total_height": 61.67935844569783,
        "radius_bottom": 13.645671683805878,
        "radius_top": 8.375906891368846,
        "n_layers": 4,
        "layer_heights": [
            9.661310646468777,
            18.676170579105044
        ],
        "connection_types": [
            "X",
            "X",
            "NONE"
        ],
        "Cost": 518.6057625952053,
        "plausibility (FAMD GMM)": 2.6986231751572873,
        "plausibility (FAMD Mahalanobis)": 0.8992745812443566,
        "plausibility (SVM)": -0.5505671298548598,
        "plausibility (One Class SVM) gamma=scale nu=0.5": 2.5363205429142397,
        "plausibility (FAMD One Class SVM) gamma=scale nu=0.5": -0.8351991644799526,
        "wave": 255730.3612485746,
        "combined": 43288986.1656241,
        "compression": 41945227.6251577,
        "tipover": 1602190.247773163,
        "torque": 360588.57261785795
    },
    {
        "id": "c11318",
        "legs": 4,
        "total_height": 92.22061323184838,
        "radius_bottom": 16.719480091877646,
        "radius_top": 10.372317292300867,
        "n_layers": 4,
        "layer_heights": [
            6.543736277263741,
            15.84353493023512
        ],
        "connection_types": [
            "NONE",
            "NONE",
            "NONE"
        ],
        "Cost": 428.42980569321264,
        "plausibility (FAMD GMM)": 3.507946903377879,
        "plausibility (FAMD Mahalanobis)": 1.5904286727791046,
        "plausibility (SVM)": 1.5920744065375723,
        "plausibility (One Class SVM) gamma=scale nu=0.5": 9.03012989939253,
        "plausibility (FAMD One Class SVM) gamma=scale nu=0.5": 2.3815851757014332,
        "wave": 1925983.5403518581,
        "combined": 35209511.474472344,
        "compression": 27627268.181535542,
        "tipover": 7409745.565097485,
        "torque": 1757575.6177320357
    },
    {
        "id": "c11723",
        "legs": 3,
        "total_height": 18.708731431281286,
        "radius_bottom": 19.154759644696405,
        "radius_top": 8.213346913836146,
        "n_layers": 4,
        "layer_heights": [
            6.543736277263741,
            13.017575937129056
        ],
        "connection_types": [
            "NONE",
            "X",
            "NONE"
        ],
        "Cost": 253.06260836669622,
        "plausibility (FAMD GMM)": 3.423686351517174,
        "plausibility (FAMD Mahalanobis)": 0.7774434508555769,
        "plausibility (SVM)": -1.0197655270068444,
        "plausibility (One Class SVM) gamma=scale nu=0.5": 8.232623882250557,
        "plausibility (FAMD One Class SVM) gamma=scale nu=0.5": 1.2943294254633582,
        "wave": 431683.37470557407,
        "combined": 80599091.45020513,
        "compression": 80391038.0550494,
        "tipover": 1129068.6576699298,
        "torque": 675592.0017197729
    },
    {
        "id": "m2315",
        "legs": 4,
        "total_height": 18.708731431281286,
        "radius_bottom": 20.994650332340566,
        "radius_top": 8.682735991085853,
        "n_layers": 5,
        "layer_heights": [
            4.60441702936756,
            15.84353493023512,
            16.172889027369262
        ],
        "connection_types": [
            "NONE",
            "NONE",
            "NONE",
            "NONE"
        ],
        "Cost": 138.7026732148027,
        "plausibility (FAMD GMM)": 6.489193450246411,
        "plausibility (FAMD Mahalanobis)": 0.7752236255079655,
        "plausibility (SVM)": -0.21929590787211373,
        "plausibility (One Class SVM) gamma=scale nu=0.5": 10.318665539067906,
        "plausibility (FAMD One Class SVM) gamma=scale nu=0.5": 1.5948025598835827,
        "wave": 686048.533132097,
        "combined": 67161404.7235381,
        "compression": 66416160.67727764,
        "tipover": 1357862.0348673784,
        "torque": 1036160.1629621582
    },
    {
        "id": "m2327",
        "legs": 3,
        "total_height": 69.59776304183762,
        "radius_bottom": 14.21440039438904,
        "radius_top": 9.203634873877972,
        "n_layers": 4,
        "layer_heights": [
            18.09884705469489,
            56.53106720121572
        ],
        "connection_types": [
            "K",
            "K",
            "X"
        ],
        "Cost": 890.0214561871418,
        "plausibility (FAMD GMM)": 6.245106078899385,
        "plausibility (FAMD Mahalanobis)": 0.27285988532662203,
        "plausibility (SVM)": 0.49122822975331326,
        "plausibility (One Class SVM) gamma=scale nu=0.5": 5.901846306402732,
        "plausibility (FAMD One Class SVM) gamma=scale nu=0.5": 0.23952994735912903,
        "wave": 175896.18450679732,
        "combined": 29959601.2521263,
        "compression": 29248163.436835065,
        "tipover": 887125.190773738,
        "torque": 247686.41643363988
    },
    {
        "id": "c11124",
        "legs": 3,
        "total_height": 18.708731431281286,
        "radius_bottom": 19.154759644696405,
        "radius_top": 8.213346913836146,
        "n_layers": 4,
        "layer_heights": [
            13.017575937129056,
            15.84353493023512
        ],
        "connection_types": [
            "NONE",
            "NONE",
            "NONE"
        ],
        "Cost": 107.69764788788106,
        "plausibility (FAMD GMM)": 5.486316092858858,
        "plausibility (FAMD Mahalanobis)": 1.4296287630083306,
        "plausibility (SVM)": -0.3713383393179206,
        "plausibility (One Class SVM) gamma=scale nu=0.5": 9.940178941853647,
        "plausibility (FAMD One Class SVM) gamma=scale nu=0.5": 0.971038343151104,
        "wave": 794612.0369708005,
        "combined": 81592681.03850591,
        "compression": 80435156.85500678,
        "tipover": 1850882.9563037388,
        "torque": 1462933.9494103421
    },
    {
        "id": "c11122",
        "legs": 3,
        "total_height": 41.79608223523681,
        "radius_bottom": 19.154759644696405,
        "radius_top": 9.203634873877972,
        "n_layers": 4,
        "layer_heights": [
            22.674884523459635,
            26.728884247510326
        ],
        "connection_types": [
            "X",
            "X",
            "NONE"
        ],
        "Cost": 535.9434124989234,
        "plausibility (FAMD GMM)": 1.450967790980101,
        "plausibility (FAMD Mahalanobis)": 0.5063042031751185,
        "plausibility (SVM)": -1.2892617752666573,
        "plausibility (One Class SVM) gamma=scale nu=0.5": 0.9777426129074307,
        "plausibility (FAMD One Class SVM) gamma=scale nu=0.5": 0.29783988150433593,
        "wave": 115438.37514365073,
        "combined": 58379159.861744985,
        "compression": 57894560.71566004,
        "tipover": 708463.2838839025,
        "torque": 121906.46150095343
    },
    {
        "id": "c11458",
        "legs": 4,
        "total_height": 61.67935844569783,
        "radius_bottom": 19.154759644696405,
        "radius_top": 9.203634873877972,
        "n_layers": 4,
        "layer_heights": [
            6.543736277263741,
            15.84353493023512
        ],
        "connection_types": [
            "NONE",
            "NONE",
            "NONE"
        ],
        "Cost": 301.97138459121805,
        "plausibility (FAMD GMM)": 2.9978759299669395,
        "plausibility (FAMD Mahalanobis)": 1.0550302841691677,
        "plausibility (SVM)": 0.6942915306392998,
        "plausibility (One Class SVM) gamma=scale nu=0.5": 4.773632605342046,
        "plausibility (FAMD One Class SVM) gamma=scale nu=0.5": -0.2264442908747224,
        "wave": 1369253.1702657342,
        "combined": 34896202.97721433,
        "compression": 30547367.932985883,
        "tipover": 4054617.2926714853,
        "torque": 1820334.9838734374
    },
    {
        "id": "c11023",
        "legs": 3,
        "total_height": 54.34289691123913,
        "radius_bottom": 19.154759644696405,
        "radius_top": 8.682735991085853,
        "n_layers": 4,
        "layer_heights": [
            13.017575937129056,
            50.62808332768375
        ],
        "connection_types": [
            "X",
            "NONE",
            "X"
        ],
        "Cost": 509.6289978971807,
        "plausibility (FAMD GMM)": 2.2788441326410025,
        "plausibility (FAMD Mahalanobis)": 0.2793558663267834,
        "plausibility (SVM)": -1.0627158597938737,
        "plausibility (One Class SVM) gamma=scale nu=0.5": 1.8003109542043347,
        "plausibility (FAMD One Class SVM) gamma=scale nu=0.5": 0.09630007873737156,
        "wave": 361785.01948578795,
        "combined": 44807076.98711115,
        "compression": 43901019.89667822,
        "tipover": 1900654.2603443116,
        "torque": 684756.9639059405
    },
    {
        "id": "c11658",
        "legs": 4,
        "total_height": 18.708731431281286,
        "radius_bottom": 19.154759644696405,
        "radius_top": 8.682735991085853,
        "n_layers": 4,
        "layer_heights": [
            4.60441702936756,
            15.84353493023512
        ],
        "connection_types": [
            "NONE",
            "NONE",
            "NONE"
        ],
        "Cost": 134.87756071488033,
        "plausibility (FAMD GMM)": 3.014621967335726,
        "plausibility (FAMD Mahalanobis)": 0.7711278598821861,
        "plausibility (SVM)": -0.16550910949717013,
        "plausibility (One Class SVM) gamma=scale nu=0.5": 8.360588934350627,
        "plausibility (FAMD One Class SVM) gamma=scale nu=0.5": 1.1961424131550977,
        "wave": 689596.4420581339,
        "combined": 59062381.30257389,
        "compression": 58152960.39275639,
        "tipover": 1412310.9463583631,
        "torque": 1087524.5179426766
    },
    {
        "id": "c10094",
        "legs": 4,
        "total_height": 61.67935844569783,
        "radius_bottom": 13.645671683805878,
        "radius_top": 9.203634873877972,
        "n_layers": 3,
        "layer_heights": [
            40.71398998887875
        ],
        "connection_types": [
            "NONE",
            "NONE"
        ],
        "Cost": 299.42004240843175,
        "plausibility (FAMD GMM)": 2.6277697102457167,
        "plausibility (FAMD Mahalanobis)": 1.123461253084298,
        "plausibility (SVM)": 1.0076831674433273,
        "plausibility (One Class SVM) gamma=scale nu=0.5": 8.433261121008783,
        "plausibility (FAMD One Class SVM) gamma=scale nu=0.5": 1.341621200290314,
        "wave": 1481703.2580678156,
        "combined": 33571048.01847552,
        "compression": 27765764.196462184,
        "tipover": 5353468.39170801,
        "torque": 1859213.1289985913
    },
    {
        "id": "c11649",
        "legs": 4,
        "total_height": 54.34289691123913,
        "radius_bottom": 19.154759644696405,
        "radius_top": 8.682735991085853,
        "n_layers": 4,
        "layer_heights": [
            40.71398998887875,
            50.62808332768375
        ],
        "connection_types": [
            "NONE",
            "X",
            "NONE"
        ],
        "Cost": 412.3649134225561,
        "plausibility (FAMD GMM)": 5.860536424988683,
        "plausibility (FAMD Mahalanobis)": 1.1222792959335932,
        "plausibility (SVM)": -0.26335241155255096,
        "plausibility (One Class SVM) gamma=scale nu=0.5": 1.9125541232888956,
        "plausibility (FAMD One Class SVM) gamma=scale nu=0.5": 0.5076013292398489,
        "wave": 925871.5597154784,
        "combined": 35308677.10887869,
        "compression": 32343727.187267072,
        "tipover": 2732485.3423574693,
        "torque": 1724404.7394096986
    },
    {
        "id": "c10362",
        "legs": 4,
        "total_height": 41.79608223523681,
        "radius_bottom": 19.154759644696405,
        "radius_top": 8.682735991085853,
        "n_layers": 4,
        "layer_heights": [
            10.197290965625525,
            40.71398998887875
        ],
        "connection_types": [
            "NONE",
            "NONE",
            "X"
        ],
        "Cost": 321.62320307082905,
        "plausibility (FAMD GMM)": 1.8103299860071798,
        "plausibility (FAMD Mahalanobis)": 0.5351968662075991,
        "plausibility (SVM)": -0.3729432462419786,
        "plausibility (One Class SVM) gamma=scale nu=0.5": 4.19082252815066,
        "plausibility (FAMD One Class SVM) gamma=scale nu=0.5": 0.449788507863385,
        "wave": 937498.3261308379,
        "combined": 37804320.46503716,
        "compression": 34973565.135466605,
        "tipover": 2683949.217424904,
        "torque": 1687408.5341987286
    },
    {
        "id": "c11702",
        "legs": 4,
        "total_height": 79.9247665214869,
        "radius_bottom": 16.719480091877646,
        "radius_top": 10.372317292300867,
        "n_layers": 4,
        "layer_heights": [
            6.543736277263741,
            10.197290965625525
        ],
        "connection_types": [
            "X",
            "X",
            "X"
        ],
        "Cost": 1334.9650201533677,
        "plausibility (FAMD GMM)": 3.0727900116068523,
        "plausibility (FAMD Mahalanobis)": 1.4804189299281802,
        "plausibility (SVM)": -0.7318061425120042,
        "plausibility (One Class SVM) gamma=scale nu=0.5": 0.6114279045958426,
        "plausibility (FAMD One Class SVM) gamma=scale nu=0.5": 1.4794002417359593,
        "wave": 237103.53690830985,
        "combined": 29864299.868262917,
        "compression": 29950460.184114836,
        "tipover": 607651.0478647405,
        "torque": 124097.72345018195
    },
    {
        "id": "c11460",
        "legs": 4,
        "total_height": 61.67935844569783,
        "radius_bottom": 18.691659977845262,
        "radius_top": 9.203634873877972,
        "n_layers": 4,
        "layer_heights": [
            50.62808332768375,
            56.230131741970254
        ],
        "connection_types": [
            "NONE",
            "NONE",
            "X"
        ],
        "Cost": 419.0516045064687,
        "plausibility (FAMD GMM)": 5.960248947848433,
        "plausibility (FAMD Mahalanobis)": 1.1236383917544726,
        "plausibility (SVM)": 0.036449106290783906,
        "plausibility (One Class SVM) gamma=scale nu=0.5": 3.529726397143097,
        "plausibility (FAMD One Class SVM) gamma=scale nu=0.5": 0.6054740903924412,
        "wave": 1175627.8771247317,
        "combined": 34379559.23484792,
        "compression": 30096878.27146786,
        "tipover": 3881974.6694249865,
        "torque": 1840570.8713789114
    },
    {
        "id": "c11692",
        "legs": 4,
        "total_height": 18.708731431281286,
        "radius_bottom": 19.468142819332982,
        "radius_top": 8.213346913836146,
        "n_layers": 4,
        "layer_heights": [
            13.017575937129056,
            15.84353493023512
        ],
        "connection_types": [
            "X",
            "X",
            "X"
        ],
        "Cost": 573.1457516882857,
        "plausibility (FAMD GMM)": 5.488565048927545,
        "plausibility (FAMD Mahalanobis)": 1.4141372943920152,
        "plausibility (SVM)": -2.3865638292741713,
        "plausibility (One Class SVM) gamma=scale nu=0.5": 3.7125582797466876,
        "plausibility (FAMD One Class SVM) gamma=scale nu=0.5": 0.924140466158482,
        "wave": 162138.53711776857,
        "combined": 68651140.2475898,
        "compression": 68356158.41232173,
        "tipover": 291881.5113692122,
        "torque": 76032.64854131785
    },
    {
        "id": "c11724",
        "legs": 4,
        "total_height": 18.708731431281286,
        "radius_bottom": 22.441147571929765,
        "radius_top": 9.203634873877972,
        "n_layers": 4,
        "layer_heights": [
            14.71134409405373,
            16.172889027369262
        ],
        "connection_types": [
            "IZ",
            "IZ",
            "NONE"
        ],
        "Cost": 326.83223399897406,
        "plausibility (FAMD GMM)": 4.182900214709491,
        "plausibility (FAMD Mahalanobis)": 1.4056238970639214,
        "plausibility (SVM)": -0.2879693011511555,
        "plausibility (One Class SVM) gamma=scale nu=0.5": 9.317366827939779,
        "plausibility (FAMD One Class SVM) gamma=scale nu=0.5": 0.7903979157003445,
        "wave": 266221.63990478637,
        "combined": 75085751.47394766,
        "compression": 74158411.43173255,
        "tipover": 427087.14196536515,
        "torque": 129294.09301358637
    },
    {
        "id": "c11258",
        "legs": 4,
        "total_height": 18.708731431281286,
        "radius_bottom": 27.848412247942864,
        "radius_top": 9.203634873877972,
        "n_layers": 4,
        "layer_heights": [
            15.84353493023512,
            18.61472307387897
        ],
        "connection_types": [
            "X",
            "X",
            "NONE"
        ],
        "Cost": 555.4047220108743,
        "plausibility (FAMD GMM)": 2.994201733363902,
        "plausibility (FAMD Mahalanobis)": 1.5788576964927175,
        "plausibility (SVM)": -2.45460015087014,
        "plausibility (One Class SVM) gamma=scale nu=0.5": 9.410849784968793,
        "plausibility (FAMD One Class SVM) gamma=scale nu=0.5": 2.183370963168567,
        "wave": 272463.5840424341,
        "combined": 104724265.28275698,
        "compression": 104466056.24321848,
        "tipover": 289508.4066583172,
        "torque": 53668.57422840453
    },
    {
        "id": "c11691",
        "legs": 4,
        "total_height": 32.60832969128558,
        "radius_bottom": 19.154759644696405,
        "radius_top": 10.035792439640886,
        "n_layers": 4,
        "layer_heights": [
            2.9329403282829567,
            6.543736277263741
        ],
        "connection_types": [
            "NONE",
            "NONE",
            "NONE"
        ],
        "Cost": 192.20860092008527,
        "plausibility (FAMD GMM)": 2.7651673287619403,
        "plausibility (FAMD Mahalanobis)": 0.9164257586303552,
        "plausibility (SVM)": 0.300893308965835,
        "plausibility (One Class SVM) gamma=scale nu=0.5": 6.552388362900844,
        "plausibility (FAMD One Class SVM) gamma=scale nu=0.5": -0.7821864890587946,
        "wave": 928690.1171532939,
        "combined": 39416601.514057726,
        "compression": 37140069.22396115,
        "tipover": 2412883.819162767,
        "torque": 1508616.711059816
    }
]