[
    {
        "id": "c11453",
        "legs": 3,
        "total_height": 42.83293090534487,
        "radius_bottom": 12.131531614719336,
        "radius_top": 8.759208300635935,
        "n_layers": 4,
        "layer_heights": [
            7.599296830426529,
            42.15696043499321
        ],
        "connection_types": [
            "NONE",
            "NONE",
            "NONE"
        ],
        "Cost": 174.4106236264176,
        "plausibility (FAMD GMM)": 5.438192129400489,
        "plausibility (FAMD Mahalanobis)": 0.9446744781907472,
        "plausibility (SVM)": 0.7683589684518162,
        "plausibility (One Class SVM) gamma=scale nu=0.5": 8.49291466991952,
        "plausibility (FAMD One Class SVM) gamma=scale nu=0.5": 2.0531563942577904,
        "wave": 1416927.4577827072,
        "combined": 43071154.180793434,
        "compression": 37443826.109535456,
        "tipover": 5352526.964000803,
        "torque": 2527992.2558401115
    },
    {
        "id": "c7108",
        "legs": 3,
        "total_height": 17.541319641971047,
        "radius_bottom": 19.347582143082285,
        "radius_top": 7.100502403895385,
        "n_layers": 4,
        "layer_heights": [
            13.960403394378055,
            17.42540776314948
        ],
        "connection_types": [
            "NONE",
            "NONE",
            "NONE"
        ],
        "Cost": 101.07628459840167,
        "plausibility (FAMD GMM)": 2.7832365426112076,
        "plausibility (FAMD Mahalanobis)": 1.863615840239083,
        "plausibility (SVM)": -0.577953376569146,
        "plausibility (One Class SVM) gamma=scale nu=0.5": 10.596573691347697,
        "plausibility (FAMD One Class SVM) gamma=scale nu=0.5": 1.5772386188812764,
        "wave": 735668.3559555106,
        "combined": 94230791.50623819,
        "compression": 93495825.23317982,
        "tipover": 1619401.7843397143,
        "torque": 1423972.95394616
    },
    {
        "id": "c3319",
        "legs": 4,
        "total_height": 62.39928906978811,
        "radius_bottom": 10.585267377739555,
        "radius_top": 10.10748640842396,
        "n_layers": 3,
        "layer_heights": [
            54.44848154057675
        ],
        "connection_types": [
            "K",
            "K"
        ],
        "Cost": 949.0851451747668,
        "plausibility (FAMD GMM)": 5.28284077645849,
        "plausibility (FAMD Mahalanobis)": 1.5188875485884317,
        "plausibility (SVM)": 1.3586198098432996,
        "plausibility (One Class SVM) gamma=scale nu=0.5": 10.518455499536353,
        "plausibility (FAMD One Class SVM) gamma=scale nu=0.5": 1.5314959840931746,
        "wave": 578986.6130059607,
        "combined": 16153081.354342459,
        "compression": 15102521.577773659,
        "tipover": 955296.6263127221,
        "torque": 376013.3422099346
    },
    {
        "id": "c11728",
        "legs": 4,
        "total_height": 92.99198459980792,
        "radius_bottom": 25.254215990286706,
        "radius_top": 11.105611817833493,
        "n_layers": 4,
        "layer_heights": [
            13.1167717624595,
            22.850603188177963
        ],
        "connection_types": [
            "XH",
            "XH",
            "K"
        ],
        "Cost": 2088.293913484116,
        "plausibility (FAMD GMM)": 6.000732694611059,
        "plausibility (FAMD Mahalanobis)": 1.8616693982410621,
        "plausibility (SVM)": 1.044605957450012,
        "plausibility (One Class SVM) gamma=scale nu=0.5": 9.863655960371677,
        "plausibility (FAMD One Class SVM) gamma=scale nu=0.5": 4.588648651628986,
        "wave": 128349.4992257604,
        "combined": 32245700.39413236,
        "compression": 31675379.472132824,
        "tipover": 476504.9673458205,
        "torque": 65627.6842852025
    },
    {
        "id": "c9968",
        "legs": 3,
        "total_height": 17.541319641971047,
        "radius_bottom": 22.693572830168364,
        "radius_top": 4.636752783789567,
        "n_layers": 4,
        "layer_heights": [
            9.24665220645395,
            17.056259084600164
        ],
        "connection_types": [
            "X",
            "X",
            "NONE"
        ],
        "Cost": 404.9311065398151,
        "plausibility (FAMD GMM)": 5.297704156435995,
        "plausibility (FAMD Mahalanobis)": 1.4226068421014273,
        "plausibility (SVM)": -2.6741056496378994,
        "plausibility (One Class SVM) gamma=scale nu=0.5": 10.23747565696748,
        "plausibility (FAMD One Class SVM) gamma=scale nu=0.5": 1.1407842298399444,
        "wave": 163098.58159137447,
        "combined": 129662480.84363684,
        "compression": 129205004.39115243,
        "tipover": 562373.0549071606,
        "torque": 121579.08967968286
    },
    {
        "id": "c9221",
        "legs": 4,
        "total_height": 62.39928906978811,
        "radius_bottom": 18.92039882124778,
        "radius_top": 10.10748640842396,
        "n_layers": 4,
        "layer_heights": [
            17.42540776314948,
            54.44848154057675
        ],
        "connection_types": [
            "X",
            "X",
            "X"
        ],
        "Cost": 1026.4931110235032,
        "plausibility (FAMD GMM)": 2.249672406071762,
        "plausibility (FAMD Mahalanobis)": 0.12770397252593074,
        "plausibility (SVM)": -1.2871210782248759,
        "plausibility (One Class SVM) gamma=scale nu=0.5": -3.1660357929930996,
        "plausibility (FAMD One Class SVM) gamma=scale nu=0.5": -0.2684529194370704,
        "wave": 159502.23816923762,
        "combined": 32638290.889100738,
        "compression": 33902253.62206711,
        "tipover": 434322.80077030585,
        "torque": 77070.86007534397
    },
    {
        "id": "c11417",
        "legs": 4,
        "total_height": 23.002602864957353,
        "radius_bottom": 27.884824335003138,
        "radius_top": 10.10748640842396,
        "n_layers": 4,
        "layer_heights": [
            19.09548147893374,
            20.071651715087423
        ],
        "connection_types": [
            "K",
            "X",
            "X"
        ],
        "Cost": 794.9318889483677,
        "plausibility (FAMD GMM)": 4.263558384055399,
        "plausibility (FAMD Mahalanobis)": 1.3241000575670314,
        "plausibility (SVM)": -2.218647664324299,
        "plausibility (One Class SVM) gamma=scale nu=0.5": 9.609401365977542,
        "plausibility (FAMD One Class SVM) gamma=scale nu=0.5": 1.738128739861864,
        "wave": 251417.8033296946,
        "combined": 45269116.93792158,
        "compression": 45392852.97618017,
        "tipover": 167419.07341679768,
        "torque": 67920.29645144624
    },
    {
        "id": "m1654",
        "legs": 4,
        "total_height": 66.82341707458929,
        "radius_bottom": 22.54138231115348,
        "radius_top": 6.102278899487283,
        "n_layers": 4,
        "layer_heights": [
            22.850603188177963,
            38.21660237209662
        ],
        "connection_types": [
            "K",
            "XH",
            "NONE"
        ],
        "Cost": 1027.0325460134825,
        "plausibility (FAMD GMM)": 6.515632959976463,
        "plausibility (FAMD Mahalanobis)": 0.22641506005230855,
        "plausibility (SVM)": -0.025877302736252883,
        "plausibility (One Class SVM) gamma=scale nu=0.5": 7.388240356333641,
        "plausibility (FAMD One Class SVM) gamma=scale nu=0.5": -0.3716299395795577,
        "wave": 51501.438809253516,
        "combined": 25080313.17131343,
        "compression": 24868468.30076024,
        "tipover": 394943.9824470855,
        "torque": 87406.76543006828
    },
    {
        "id": "c10867",
        "legs": 4,
        "total_height": 23.002602864957353,
        "radius_bottom": 27.884824335003138,
        "radius_top": 11.105611817833493,
        "n_layers": 4,
        "layer_heights": [
            19.09548147893374,
            20.071651715087423
        ],
        "connection_types": [
            "X",
            "X",
            "K"
        ],
        "Cost": 766.3949390103703,
        "plausibility (FAMD GMM)": 4.450036425766459,
        "plausibility (FAMD Mahalanobis)": 1.3160348069025023,
        "plausibility (SVM)": -2.0624114477165185,
        "plausibility (One Class SVM) gamma=scale nu=0.5": 9.354582949280564,
        "plausibility (FAMD One Class SVM) gamma=scale nu=0.5": 1.9610692515932868,
        "wave": 264131.9799343938,
        "combined": 81633342.99071264,
        "compression": 81361586.43995094,
        "tipover": 282361.70741773647,
        "torque": 48651.71642266551
    },
    {
        "id": "c11384",
        "legs": 4,
        "total_height": 87.37244929648898,
        "radius_bottom": 17.109958239742937,
        "radius_top": 12.06370949745838,
        "n_layers": 4,
        "layer_heights": [
            9.24665220645395,
            17.42540776314948
        ],
        "connection_types": [
            "NONE",
            "Z",
            "NONE"
        ],
        "Cost": 516.3741867031061,
        "plausibility (FAMD GMM)": 3.758614993633725,
        "plausibility (FAMD Mahalanobis)": 1.535723081811674,
        "plausibility (SVM)": 1.8405787268158869,
        "plausibility (One Class SVM) gamma=scale nu=0.5": 8.617529242331019,
        "plausibility (FAMD One Class SVM) gamma=scale nu=0.5": 2.3009045403959796,
        "wave": 1675737.326354668,
        "combined": 35168685.03018517,
        "compression": 26829988.65432645,
        "tipover": 8367296.973476514,
        "torque": 1360119.7975295105
    },
    {
        "id": "c9145",
        "legs": 3,
        "total_height": 17.541319641971047,
        "radius_bottom": 17.109958239742937,
        "radius_top": 7.100502403895385,
        "n_layers": 4,
        "layer_heights": [
            7.445846983469463,
            7.599296830426529
        ],
        "connection_types": [
            "NONE",
            "NONE",
            "NONE"
        ],
        "Cost": 97.48393781191051,
        "plausibility (FAMD GMM)": 7.937784890134861,
        "plausibility (FAMD Mahalanobis)": 0.92019763826502,
        "plausibility (SVM)": -0.33850304064144643,
        "plausibility (One Class SVM) gamma=scale nu=0.5": 10.479594294418606,
        "plausibility (FAMD One Class SVM) gamma=scale nu=0.5": 2.1371810928963964,
        "wave": 751443.0938728914,
        "combined": 80181744.82638092,
        "compression": 79196755.0025619,
        "tipover": 1702794.3147797794,
        "torque": 1520619.4000126668
    },
    {
        "id": "c11844",
        "legs": 3,
        "total_height": 65.21088912804947,
        "radius_bottom": 19.347582143082285,
        "radius_top": 11.105611817833493,
        "n_layers": 4,
        "layer_heights": [
            9.24665220645395,
            14.848844498073804
        ],
        "connection_types": [
            "NONE",
            "NONE",
            "NONE"
        ],
        "Cost": 254.89547584249655,
        "plausibility (FAMD GMM)": 3.4800905177476418,
        "plausibility (FAMD Mahalanobis)": 1.1700032664084499,
        "plausibility (SVM)": 0.8894312380143483,
        "plausibility (One Class SVM) gamma=scale nu=0.5": 5.4368814052290535,
        "plausibility (FAMD One Class SVM) gamma=scale nu=0.5": 0.46532260264575953,
        "wave": 1820212.6357865012,
        "combined": 45790365.57509338,
        "compression": 39375363.15673732,
        "tipover": 6674843.206263093,
        "torque": 2469216.024824644
    },
    {
        "id": "m1839",
        "legs": 4,
        "total_height": 64.92824710519619,
        "radius_bottom": 15.26770338779989,
        "radius_top": 12.06370949745838,
        "n_layers": 3,
        "layer_heights": [
            59.56832484710567
        ],
        "connection_types": [
            "K",
            "K"
        ],
        "Cost": 1046.8968719032569,
        "plausibility (FAMD GMM)": 5.7226018108065215,
        "plausibility (FAMD Mahalanobis)": 1.2030531494742984,
        "plausibility (SVM)": 1.3111545227509915,
        "plausibility (One Class SVM) gamma=scale nu=0.5": 9.028007551877812,
        "plausibility (FAMD One Class SVM) gamma=scale nu=0.5": 0.5448971749091687,
        "wave": 618769.7376523116,
        "combined": 15899161.285310926,
        "compression": 15467668.820907366,
        "tipover": 610415.0050021044,
        "torque": 199749.79621858368
    },
    {
        "id": "c11011",
        "legs": 4,
        "total_height": 87.37244929648898,
        "radius_bottom": 17.109958239742937,
        "radius_top": 12.06370949745838,
        "n_layers": 4,
        "layer_heights": [
            8.429072794452487,
            22.65485478831501
        ],
        "connection_types": [
            "NONE",
            "Z",
            "NONE"
        ],
        "Cost": 526.2696038715466,
        "plausibility (FAMD GMM)": 3.749310127747344,
        "plausibility (FAMD Mahalanobis)": 1.4674270526450883,
        "plausibility (SVM)": 1.8409801309816722,
        "plausibility (One Class SVM) gamma=scale nu=0.5": 8.573172111318758,
        "plausibility (FAMD One Class SVM) gamma=scale nu=0.5": 1.944377577162216,
        "wave": 1741884.6286371066,
        "combined": 34298177.75132235,
        "compression": 27608847.307699487,
        "tipover": 7769082.042745243,
        "torque": 1276314.7543687453
    },
    {
        "id": "c11623",
        "legs": 3,
        "total_height": 17.541319641971047,
        "radius_bottom": 21.564453478914743,
        "radius_top": 7.100502403895385,
        "n_layers": 4,
        "layer_heights": [
            7.445846983469463,
            7.599296830426529
        ],
        "connection_types": [
            "X",
            "NONE",
            "NONE"
        ],
        "Cost": 303.28556915447996,
        "plausibility (FAMD GMM)": 5.49110023738686,
        "plausibility (FAMD Mahalanobis)": 0.5692865032455314,
        "plausibility (SVM)": -1.5270903992584883,
        "plausibility (One Class SVM) gamma=scale nu=0.5": 9.550088852293516,
        "plausibility (FAMD One Class SVM) gamma=scale nu=0.5": 0.9594394146365612,
        "wave": 201035.5067002204,
        "combined": 109897896.94306637,
        "compression": 109357406.18657106,
        "tipover": 667825.4709451714,
        "torque": 174793.83946145058
    },
    {
        "id": "c11530",
        "legs": 4,
        "total_height": 62.39928906978811,
        "radius_bottom": 11.105611817833493,
        "radius_top": 10.585267377739555,
        "n_layers": 3,
        "layer_heights": [
            54.44848154057675
        ],
        "connection_types": [
            "NONE",
            "K"
        ],
        "Cost": 457.0977192353401,
        "plausibility (FAMD GMM)": 5.223241511958983,
        "plausibility (FAMD Mahalanobis)": 1.4538329047124174,
        "plausibility (SVM)": 1.519504922801668,
        "plausibility (One Class SVM) gamma=scale nu=0.5": 10.354904405511498,
        "plausibility (FAMD One Class SVM) gamma=scale nu=0.5": 1.2904352748649135,
        "wave": 1345935.8568319331,
        "combined": 33172507.8924163,
        "compression": 26472715.662696898,
        "tipover": 6307336.033551111,
        "torque": 1944792.3596382567
    },
    {
        "id": "c4895",
        "legs": 4,
        "total_height": 76.58091079186657,
        "radius_bottom": 15.007272248322757,
        "radius_top": 11.105611817833493,
        "n_layers": 4,
        "layer_heights": [
            20.071651715087423,
            70.25904401432776
        ],
        "connection_types": [
            "NONE",
            "NONE",
            "NONE"
        ],
        "Cost": 369.54377815532,
        "plausibility (FAMD GMM)": 3.31697267089573,
        "plausibility (FAMD Mahalanobis)": 0.04912086385855979,
        "plausibility (SVM)": 1.565356819598629,
        "plausibility (One Class SVM) gamma=scale nu=0.5": 7.305911576074012,
        "plausibility (FAMD One Class SVM) gamma=scale nu=0.5": -0.24964894598262966,
        "wave": 1783790.9763534402,
        "combined": 34899063.74659244,
        "compression": 27586008.128086574,
        "tipover": 7069516.73705638,
        "torque": 1845520.5666926317
    },
    {
        "id": "c11684",
        "legs": 3,
        "total_height": 62.39928906978811,
        "radius_bottom": 21.564453478914743,
        "radius_top": 8.973838804250029,
        "n_layers": 4,
        "layer_heights": [
            17.056259084600164,
            20.071651715087423
        ],
        "connection_types": [
            "X",
            "X",
            "NONE"
        ],
        "Cost": 654.1176275516117,
        "plausibility (FAMD GMM)": 4.8583555016665585,
        "plausibility (FAMD Mahalanobis)": 0.7515761427690361,
        "plausibility (SVM)": -1.1770700303069694,
        "plausibility (One Class SVM) gamma=scale nu=0.5": 0.0883614849531078,
        "plausibility (FAMD One Class SVM) gamma=scale nu=0.5": -0.334322754952602,
        "wave": 246725.33211605862,
        "combined": 51612332.710115604,
        "compression": 50973203.80418096,
        "tipover": 1066299.9202270568,
        "torque": 260357.29893761288
    },
    {
        "id": "c10970",
        "legs": 3,
        "total_height": 17.541319641971047,
        "radius_bottom": 22.693572830168364,
        "radius_top": 8.973838804250029,
        "n_layers": 4,
        "layer_heights": [
            9.24665220645395,
            17.42540776314948
        ],
        "connection_types": [
            "X",
            "NONE",
            "NONE"
        ],
        "Cost": 320.45337795899604,
        "plausibility (FAMD GMM)": 5.485276612753671,
        "plausibility (FAMD Mahalanobis)": 1.176283314576573,
        "plausibility (SVM)": -1.3879416009740217,
        "plausibility (One Class SVM) gamma=scale nu=0.5": 9.265508468919526,
        "plausibility (FAMD One Class SVM) gamma=scale nu=0.5": 0.5303547035909411,
        "wave": 179809.78955994718,
        "combined": 104750995.65994051,
        "compression": 104206831.49107899,
        "tipover": 664589.4077879918,
        "torque": 154274.26215144125
    },
    {
        "id": "c9815",
        "legs": 4,
        "total_height": 92.99198459980792,
        "radius_bottom": 25.254215990286706,
        "radius_top": 11.105611817833493,
        "n_layers": 4,
        "layer_heights": [
            39.17491250952842,
            42.15696043499321
        ],
        "connection_types": [
            "K",
            "K",
            "K"
        ],
        "Cost": 1654.2840429724067,
        "plausibility (FAMD GMM)": 6.90064199624066,
        "plausibility (FAMD Mahalanobis)": 1.3030649903005993,
        "plausibility (SVM)": 0.8681233551897471,
        "plausibility (One Class SVM) gamma=scale nu=0.5": 9.699212805292879,
        "plausibility (FAMD One Class SVM) gamma=scale nu=0.5": 0.6655240195393777,
        "wave": 55928.60313897272,
        "combined": 19731427.561180595,
        "compression": 19662920.303645328,
        "tipover": 347644.9562378745,
        "torque": 75074.49605270708
    },
    {
        "id": "c10635",
        "legs": 3,
        "total_height": 17.541319641971047,
        "radius_bottom": 22.693572830168364,
        "radius_top": 7.100502403895385,
        "n_layers": 4,
        "layer_heights": [
            13.1167717624595,
            17.056259084600164
        ],
        "connection_types": [
            "X",
            "NONE",
            "NONE"
        ],
        "Cost": 302.57576118238705,
        "plausibility (FAMD GMM)": 3.323550817346605,
        "plausibility (FAMD Mahalanobis)": 1.6117208019426208,
        "plausibility (SVM)": -1.6704320532874042,
        "plausibility (One Class SVM) gamma=scale nu=0.5": 9.95773721224174,
        "plausibility (FAMD One Class SVM) gamma=scale nu=0.5": 1.0377620435358885,
        "wave": 237542.19831134315,
        "combined": 121997544.60226373,
        "compression": 121613675.16911149,
        "tipover": 590445.4205904905,
        "torque": 110896.32982071074
    },
    {
        "id": "c11837",
        "legs": 3,
        "total_height": 17.541319641971047,
        "radius_bottom": 22.693572830168364,
        "radius_top": 7.100502403895385,
        "n_layers": 4,
        "layer_heights": [
            9.24665220645395,
            17.056259084600164
        ],
        "connection_types": [
            "X",
            "NONE",
            "NONE"
        ],
        "Cost": 309.7515816611007,
        "plausibility (FAMD GMM)": 5.191021256899119,
        "plausibility (FAMD Mahalanobis)": 1.2565336322949523,
        "plausibility (SVM)": -1.6504869718554196,
        "plausibility (One Class SVM) gamma=scale nu=0.5": 9.889382805751318,
        "plausibility (FAMD One Class SVM) gamma=scale nu=0.5": 0.7046900878063678,
        "wave": 179367.10175913002,
        "combined": 117783447.28722535,
        "compression": 117235797.70940849,
        "tipover": 651557.2451508595,
        "torque": 175913.42614361542
    },
    {
        "id": "c10679",
        "legs": 3,
        "total_height": 53.22186980872247,
        "radius_bottom": 21.564453478914743,
        "radius_top": 11.105611817833493,
        "n_layers": 4,
        "layer_heights": [
            38.56816390611271,
            49.62334724479272
        ],
        "connection_types": [
            "NONE",
            "X",
            "NONE"
        ],
        "Cost": 370.13168086396223,
        "plausibility (FAMD GMM)": 6.435371018100245,
        "plausibility (FAMD Mahalanobis)": 0.9999674629935824,
        "plausibility (SVM)": -0.278387158645065,
        "plausibility (One Class SVM) gamma=scale nu=0.5": 3.295257903250244,
        "plausibility (FAMD One Class SVM) gamma=scale nu=0.5": 0.7688167644344723,
        "wave": 1139383.4352326759,
        "combined": 46202647.14317343,
        "compression": 42468867.65474597,
        "tipover": 4107672.2826016415,
        "torque": 2131779.021177223
    },
    {
        "id": "m2224",
        "legs": 4,
        "total_height": 17.541319641971047,
        "radius_bottom": 22.693572830168364,
        "radius_top": 4.97754914857337,
        "n_layers": 4,
        "layer_heights": [
            9.24665220645395,
            13.960403394378055
        ],
        "connection_types": [
            "NONE",
            "X",
            "NONE"
        ],
        "Cost": 260.4087385794862,
        "plausibility (FAMD GMM)": 3.001217596404648,
        "plausibility (FAMD Mahalanobis)": 1.1727825159814553,
        "plausibility (SVM)": -1.743943493469137,
        "plausibility (One Class SVM) gamma=scale nu=0.5": 9.86313604125717,
        "plausibility (FAMD One Class SVM) gamma=scale nu=0.5": 1.156101723698825,
        "wave": 382692.6110575343,
        "combined": 96871912.91358644,
        "compression": 96401490.76639223,
        "tipover": 601572.527846792,
        "torque": 618756.6655404577
    },
    {
        "id": "c11819",
        "legs": 3,
        "total_height": 23.002602864957353,
        "radius_bottom": 21.564453478914743,
        "radius_top": 8.973838804250029,
        "n_layers": 4,
        "layer_heights": [
            7.599296830426529,
            19.396398256879653
        ],
        "connection_types": [
            "NONE",
            "X",
            "NONE"
        ],
        "Cost": 289.88870090250674,
        "plausibility (FAMD GMM)": 1.5214522416779108,
        "plausibility (FAMD Mahalanobis)": 0.6298330363448414,
        "plausibility (SVM)": -1.0615402557889175,
        "plausibility (One Class SVM) gamma=scale nu=0.5": 7.691323101470207,
        "plausibility (FAMD One Class SVM) gamma=scale nu=0.5": 0.47936002856480187,
        "wave": 463822.29456156143,
        "combined": 80566167.80477254,
        "compression": 79739738.32925306,
        "tipover": 1227880.8400422053,
        "torque": 687929.5125741038
    },
    {
        "id": "c11545",
        "legs": 3,
        "total_height": 33.61194778792329,
        "radius_bottom": 21.564453478914743,
        "radius_top": 7.100502403895385,
        "n_layers": 4,
        "layer_heights": [
            7.599296830426529,
            19.396398256879653
        ],
        "connection_types": [
            "X",
            "X",
            "NONE"
        ],
        "Cost": 538.004313050703,
        "plausibility (FAMD GMM)": 7.443286553282635,
        "plausibility (FAMD Mahalanobis)": 0.33754733845362284,
        "plausibility (SVM)": -1.922395213444394,
        "plausibility (One Class SVM) gamma=scale nu=0.5": 4.34538121619827,
        "plausibility (FAMD One Class SVM) gamma=scale nu=0.5": 0.2678133919157908,
        "wave": 149503.84742019884,
        "combined": 63915901.14908055,
        "compression": 63669788.497615516,
        "tipover": 701480.777246695,
        "torque": 244918.65925502783
    },
    {
        "id": "m2242",
        "legs": 3,
        "total_height": 40.72605377217881,
        "radius_bottom": 22.54138231115348,
        "radius_top": 11.105611817833493,
        "n_layers": 4,
        "layer_heights": [
            22.850603188177963,
            38.21660237209662
        ],
        "connection_types": [
            "NONE",
            "NONE",
            "NONE"
        ],
        "Cost": 184.60993761387323,
        "plausibility (FAMD GMM)": 3.62899752167457,
        "plausibility (FAMD Mahalanobis)": 0.8263706358695875,
        "plausibility (SVM)": 0.11530621466497815,
        "plausibility (One Class SVM) gamma=scale nu=0.5": 7.192212578106819,
        "plausibility (FAMD One Class SVM) gamma=scale nu=0.5": 0.32372665593649863,
        "wave": 1274764.2080047664,
        "combined": 53067467.74324817,
        "compression": 49790948.17904122,
        "tipover": 3815106.8994985977,
        "torque": 2080744.0098679587
    },
    {
        "id": "c11359",
        "legs": 4,
        "total_height": 70.6391295790835,
        "radius_bottom": 21.564453478914743,
        "radius_top": 11.105611817833493,
        "n_layers": 4,
        "layer_heights": [
            8.429072794452487,
            13.960403394378055
        ],
        "connection_types": [
            "NONE",
            "NONE",
            "NONE"
        ],
        "Cost": 348.45963166045766,
        "plausibility (FAMD GMM)": 3.969734770745462,
        "plausibility (FAMD Mahalanobis)": 1.4152389339300546,
        "plausibility (SVM)": 0.8800829582681566,
        "plausibility (One Class SVM) gamma=scale nu=0.5": 5.810125892793291,
        "plausibility (FAMD One Class SVM) gamma=scale nu=0.5": 1.7636682777535189,
        "wave": 1553582.6656343522,
        "combined": 35255070.409762874,
        "compression": 30253523.741168283,
        "tipover": 4876457.138073934,
        "torque": 1831471.221973935
    },
    {
        "id": "c10462",
        "legs": 4,
        "total_height": 62.39928906978811,
        "radius_bottom": 21.564453478914743,
        "radius_top": 8.973838804250029,
        "n_layers": 4,
        "layer_heights": [
            17.056259084600164,
            19.09548147893374
        ],
        "connection_types": [
            "X",
            "X",
            "X"
        ],
        "Cost": 1153.3189860954976,
        "plausibility (FAMD GMM)": 4.740491992594038,
        "plausibility (FAMD Mahalanobis)": 0.7735334870483239,
        "plausibility (SVM)": -1.6926080660836127,
        "plausibility (One Class SVM) gamma=scale nu=0.5": -2.412695559156383,
        "plausibility (FAMD One Class SVM) gamma=scale nu=0.5": -0.31503281989571263,
        "wave": 166049.70292725795,
        "combined": 37656324.93022121,
        "compression": 37218097.17311048,
        "tipover": 395469.7610522446,
        "torque": 66941.44589038468
    },
    {
        "id": "c11780",
        "legs": 4,
        "total_height": 17.541319641971047,
        "radius_bottom": 21.564453478914743,
        "radius_top": 11.105611817833493,
        "n_layers": 4,
        "layer_heights": [
            8.429072794452487,
            13.1167717624595
        ],
        "connection_types": [
            "NONE",
            "NONE",
            "NONE"
        ],
        "Cost": 144.5134891648456,
        "plausibility (FAMD GMM)": 1.3793630593075816,
        "plausibility (FAMD Mahalanobis)": 0.6797817348091456,
        "plausibility (SVM)": -0.09339982625684717,
        "plausibility (One Class SVM) gamma=scale nu=0.5": 9.484780238280964,
        "plausibility (FAMD One Class SVM) gamma=scale nu=0.5": 0.2579297797759921,
        "wave": 721525.720224389,
        "combined": 61777284.30799928,
        "compression": 60755113.37442269,
        "tipover": 1490737.9912198645,
        "torque": 929694.6652663853
    },
    {
        "id": "c11773",
        "legs": 3,
        "total_height": 17.541319641971047,
        "radius_bottom": 21.564453478914743,
        "radius_top": 7.100502403895385,
        "n_layers": 4,
        "layer_heights": [
            13.960403394378055,
            17.42540776314948
        ],
        "connection_types": [
            "NONE",
            "X",
            "NONE"
        ],
        "Cost": 197.5096856499167,
        "plausibility (FAMD GMM)": 2.757687579667847,
        "plausibility (FAMD Mahalanobis)": 1.7653368098814324,
        "plausibility (SVM)": -1.4640138536042335,
        "plausibility (One Class SVM) gamma=scale nu=0.5": 9.575883819038129,
        "plausibility (FAMD One Class SVM) gamma=scale nu=0.5": 1.3412996806342736,
        "wave": 599644.4714551659,
        "combined": 107979897.57062641,
        "compression": 107303015.54043806,
        "tipover": 1434555.7304337183,
        "torque": 1209127.0859478295
    },
    {
        "id": "c11063",
        "legs": 3,
        "total_height": 33.61194778792329,
        "radius_bottom": 21.564453478914743,
        "radius_top": 7.100502403895385,
        "n_layers": 4,
        "layer_heights": [
            19.09548147893374,
            19.396398256879653
        ],
        "connection_types": [
            "NONE",
            "NONE",
            "X"
        ],
        "Cost": 283.63162485445207,
        "plausibility (FAMD GMM)": 1.6347141229819142,
        "plausibility (FAMD Mahalanobis)": 0.6099673881362341,
        "plausibility (SVM)": -1.0981767766818442,
        "plausibility (One Class SVM) gamma=scale nu=0.5": 8.111945012840627,
        "plausibility (FAMD One Class SVM) gamma=scale nu=0.5": 0.5054432840282814,
        "wave": 677214.7917003884,
        "combined": 70323468.74925144,
        "compression": 69100484.1299994,
        "tipover": 1790061.217222545,
        "torque": 1463061.590989626
    },
    {
        "id": "c11505",
        "legs": 3,
        "total_height": 17.541319641971047,
        "radius_bottom": 19.347582143082285,
        "radius_top": 11.105611817833493,
        "n_layers": 4,
        "layer_heights": [
            13.960403394378055,
            17.42540776314948
        ],
        "connection_types": [
            "NONE",
            "NONE",
            "NONE"
        ],
        "Cost": 115.84982391700663,
        "plausibility (FAMD GMM)": 2.964888661655843,
        "plausibility (FAMD Mahalanobis)": 1.6313031111187304,
        "plausibility (SVM)": -0.013918795542669837,
        "plausibility (One Class SVM) gamma=scale nu=0.5": 10.41389082614701,
        "plausibility (FAMD One Class SVM) gamma=scale nu=0.5": 1.1578135496376714,
        "wave": 852708.758319667,
        "combined": 69060151.64431038,
        "compression": 67389607.04836889,
        "tipover": 2081096.6505665537,
        "torque": 1307778.82653844
    },
    {
        "id": "c11650",
        "legs": 4,
        "total_height": 62.39928906978811,
        "radius_bottom": 11.105611817833493,
        "radius_top": 10.585267377739555,
        "n_layers": 4,
        "layer_heights": [
            42.15696043499321,
            54.44848154057675
        ],
        "connection_types": [
            "NONE",
            "X",
            "X"
        ],
        "Cost": 601.4062007183059,
        "plausibility (FAMD GMM)": 2.5869832614966075,
        "plausibility (FAMD Mahalanobis)": 1.0232984835624757,
        "plausibility (SVM)": 0.20024225295059717,
        "plausibility (One Class SVM) gamma=scale nu=0.5": 5.567804172774144,
        "plausibility (FAMD One Class SVM) gamma=scale nu=0.5": 0.7560257263937178,
        "wave": 1118081.3617619616,
        "combined": 32931163.77918851,
        "compression": 27207185.456269715,
        "tipover": 5110411.381735411,
        "torque": 1991931.5943337204
    },
    {
        "id": "c11382",
        "legs": 4,
        "total_height": 62.39928906978811,
        "radius_bottom": 11.105611817833493,
        "radius_top": 10.585267377739555,
        "n_layers": 3,
        "layer_heights": [
            54.44848154057675
        ],
        "connection_types": [
            "NONE",
            "NONE"
        ],
        "Cost": 309.48514912674756,
        "plausibility (FAMD GMM)": 5.223241511958983,
        "plausibility (FAMD Mahalanobis)": 1.4538329047124174,
        "plausibility (SVM)": 1.3861453337693157,
        "plausibility (One Class SVM) gamma=scale nu=0.5": 10.316528339263511,
        "plausibility (FAMD One Class SVM) gamma=scale nu=0.5": 1.2904352748649135,
        "wave": 1631173.7477477817,
        "combined": 34579964.89558082,
        "compression": 27386461.794323318,
        "tipover": 6925233.860524461,
        "torque": 1892075.3416801551
    },
    {
        "id": "c10960",
        "legs": 4,
        "total_height": 17.541319641971047,
        "radius_bottom": 27.884824335003138,
        "radius_top": 11.105611817833493,
        "n_layers": 4,
        "layer_heights": [
            13.1167717624595,
            13.960403394378055
        ],
        "connection_types": [
            "X",
            "X",
            "X"
        ],
        "Cost": 753.5442887959242,
        "plausibility (FAMD GMM)": 6.163125018084921,
        "plausibility (FAMD Mahalanobis)": 1.1111002140149222,
        "plausibility (SVM)": -2.8071841560735797,
        "plausibility (One Class SVM) gamma=scale nu=0.5": 9.18886002289237,
        "plausibility (FAMD One Class SVM) gamma=scale nu=0.5": 1.146129273895884,
        "wave": 198629.91488088513,
        "combined": 100543928.32384364,
        "compression": 100519106.49137834,
        "tipover": 277377.2737989134,
        "torque": 49645.986676724766
    },
    {
        "id": "m2198",
        "legs": 3,
        "total_height": 17.541319641971047,
        "radius_bottom": 22.693572830168364,
        "radius_top": 5.453477484035849,
        "n_layers": 4,
        "layer_heights": [
            9.24665220645395,
            17.056259084600164
        ],
        "connection_types": [
            "X",
            "X",
            "NONE"
        ],
        "Cost": 414.76157812330257,
        "plausibility (FAMD GMM)": 5.25045571361392,
        "plausibility (FAMD Mahalanobis)": 1.365311031391182,
        "plausibility (SVM)": -2.5606360290759986,
        "plausibility (One Class SVM) gamma=scale nu=0.5": 9.471447482995838,
        "plausibility (FAMD One Class SVM) gamma=scale nu=0.5": 0.9730757226737321,
        "wave": 162085.54712579778,
        "combined": 124414091.72518457,
        "compression": 123956635.21046238,
        "tipover": 560764.5163586966,
        "torque": 125569.82406448407
    },
    {
        "id": "c11625",
        "legs": 3,
        "total_height": 44.438895795085756,
        "radius_bottom": 19.347582143082285,
        "radius_top": 8.973838804250029,
        "n_layers": 4,
        "layer_heights": [
            7.445846983469463,
            39.17491250952842
        ],
        "connection_types": [
            "NONE",
            "X",
            "X"
        ],
        "Cost": 528.1688247604519,
        "plausibility (FAMD GMM)": 3.9896306495403664,
        "plausibility (FAMD Mahalanobis)": 0.25963056295333264,
        "plausibility (SVM)": -1.0984957393474182,
        "plausibility (One Class SVM) gamma=scale nu=0.5": 2.711275455678468,
        "plausibility (FAMD One Class SVM) gamma=scale nu=0.5": 0.20910018931041563,
        "wave": 553220.6365123072,
        "combined": 93390766.4345068,
        "compression": 93428621.18756273,
        "tipover": 1718402.5124496762,
        "torque": 780721.8116595683
    },
    {
        "id": "c10567",
        "legs": 3,
        "total_height": 44.438895795085756,
        "radius_bottom": 22.693572830168364,
        "radius_top": 8.973838804250029,
        "n_layers": 4,
        "layer_heights": [
            13.1167717624595,
            13.960403394378055
        ],
        "connection_types": [
            "X",
            "X",
            "NONE"
        ],
        "Cost": 607.7066335227792,
        "plausibility (FAMD GMM)": 5.531733186464264,
        "plausibility (FAMD Mahalanobis)": 0.5303669520671503,
        "plausibility (SVM)": -1.587323799342149,
        "plausibility (One Class SVM) gamma=scale nu=0.5": 2.0607942935647863,
        "plausibility (FAMD One Class SVM) gamma=scale nu=0.5": -0.4526570157129157,
        "wave": 251366.59832634358,
        "combined": 58962577.051214054,
        "compression": 58004815.914373145,
        "tipover": 1117968.4865366044,
        "torque": 418787.51091395674
    },
    {
        "id": "c6958",
        "legs": 3,
        "total_height": 65.21088912804947,
        "radius_bottom": 19.347582143082285,
        "radius_top": 11.105611817833493,
        "n_layers": 4,
        "layer_heights": [
            39.17491250952842,
            54.44848154057675
        ],
        "connection_types": [
            "NONE",
            "X",
            "X"
        ],
        "Cost": 560.4921027927323,
        "plausibility (FAMD GMM)": 1.1553127588482734,
        "plausibility (FAMD Mahalanobis)": 0.5814293127027534,
        "plausibility (SVM)": -0.4875296232911288,
        "plausibility (One Class SVM) gamma=scale nu=0.5": 1.2402385653475214,
        "plausibility (FAMD One Class SVM) gamma=scale nu=0.5": -0.04693846049619843,
        "wave": 1187011.5789726917,
        "combined": 42883378.02602481,
        "compression": 38401131.45540842,
        "tipover": 4631805.319439684,
        "torque": 2261658.1237908155
    },
    {
        "id": "m2172",
        "legs": 3,
        "total_height": 50.25014415161317,
        "radius_bottom": 22.693572830168364,
        "radius_top": 10.10748640842396,
        "n_layers": 4,
        "layer_heights": [
            25.7766556696727,
            43.847359273443104
        ],
        "connection_types": [
            "NONE",
            "X",
            "NONE"
        ],
        "Cost": 389.669874137219,
        "plausibility (FAMD GMM)": 1.305971358722258,
        "plausibility (FAMD Mahalanobis)": 0.601388483598633,
        "plausibility (SVM)": -0.5623540060301955,
        "plausibility (One Class SVM) gamma=scale nu=0.5": 3.6460609017367105,
        "plausibility (FAMD One Class SVM) gamma=scale nu=0.5": -0.011970543818542012,
        "wave": 891649.3994368576,
        "combined": 50874600.149052374,
        "compression": 48461175.55627735,
        "tipover": 2881191.1436361074,
        "torque": 1636950.5625170465
    },
    {
        "id": "c11629",
        "legs": 4,
        "total_height": 70.6391295790835,
        "radius_bottom": 12.131531614719336,
        "radius_top": 8.759208300635935,
        "n_layers": 4,
        "layer_heights": [
            8.429072794452487,
            42.15696043499321
        ],
        "connection_types": [
            "NONE",
            "NONE",
            "NONE"
        ],
        "Cost": 332.4278902646669,
        "plausibility (FAMD GMM)": 4.074829105228098,
        "plausibility (FAMD Mahalanobis)": 0.6653706317284138,
        "plausibility (SVM)": 1.3776143002048635,
        "plausibility (One Class SVM) gamma=scale nu=0.5": 8.014172361480385,
        "plausibility (FAMD One Class SVM) gamma=scale nu=0.5": -0.30067626577858775,
        "wave": 1646028.5170584195,
        "combined": 34057808.792216375,
        "compression": 27216456.373981968,
        "tipover": 6473068.7719786735,
        "torque": 1784590.3436865811
    },
    {
        "id": "m2292",
        "legs": 3,
        "total_height": 41.15076949031787,
        "radius_bottom": 22.166202051151185,
        "radius_top": 8.973838804250029,
        "n_layers": 4,
        "layer_heights": [
            11.947971811341251,
            40.878847930028684
        ],
        "connection_types": [
            "NONE",
            "NONE",
            "NONE"
        ],
        "Cost": 176.27054847505278,
        "plausibility (FAMD GMM)": 0.9481855913574697,
        "plausibility (FAMD Mahalanobis)": 0.4960268760955799,
        "plausibility (SVM)": -0.11895777779874583,
        "plausibility (One Class SVM) gamma=scale nu=0.5": 6.949233834029979,
        "plausibility (FAMD One Class SVM) gamma=scale nu=0.5": 0.045959055049833,
        "wave": 1191959.1168460106,
        "combined": 55420747.564227045,
        "compression": 52493371.16154148,
        "tipover": 3312790.44739922,
        "torque": 2116746.225709082
    },
    {
        "id": "c11514",
        "legs": 3,
        "total_height": 62.39928906978811,
        "radius_bottom": 19.347582143082285,
        "radius_top": 8.973838804250029,
        "n_layers": 4,
        "layer_heights": [
            17.056259084600164,
            17.42540776314948
        ],
        "connection_types": [
            "X",
            "X",
            "X"
        ],
        "Cost": 921.7285969901745,
        "plausibility (FAMD GMM)": 4.153553312823202,
        "plausibility (FAMD Mahalanobis)": 0.7411535166023768,
        "plausibility (SVM)": -1.5994497214674133,
        "plausibility (One Class SVM) gamma=scale nu=0.5": -1.749456605531698,
        "plausibility (FAMD One Class SVM) gamma=scale nu=0.5": -0.46926081123485197,
        "wave": 261940.84091967696,
        "combined": 48389590.03474302,
        "compression": 47837835.18942264,
        "tipover": 777069.4762780224,
        "torque": 109562.48064503052
    },
    {
        "id": "c11548",
        "legs": 4,
        "total_height": 40.72605377217881,
        "radius_bottom": 22.693572830168364,
        "radius_top": 9.316306956374623,
        "n_layers": 4,
        "layer_heights": [
            8.429072794452487,
            13.960403394378055
        ],
        "connection_types": [
            "NONE",
            "NONE",
            "NONE"
        ],
        "Cost": 224.1681978681574,
        "plausibility (FAMD GMM)": 4.932373715895645,
        "plausibility (FAMD Mahalanobis)": 0.608502657345914,
        "plausibility (SVM)": -0.010805737373322355,
        "plausibility (One Class SVM) gamma=scale nu=0.5": 6.222555028187514,
        "plausibility (FAMD One Class SVM) gamma=scale nu=0.5": -0.4663012785082863,
        "wave": 1001060.4732595711,
        "combined": 42219243.042840555,
        "compression": 39950328.868723035,
        "tipover": 2455270.563925637,
        "torque": 1563535.9566426089
    },
    {
        "id": "c10809",
        "legs": 3,
        "total_height": 17.541319641971047,
        "radius_bottom": 22.693572830168364,
        "radius_top": 7.100502403895385,
        "n_layers": 4,
        "layer_heights": [
            13.1167717624595,
            13.960403394378055
        ],
        "connection_types": [
            "X",
            "X",
            "NONE"
        ],
        "Cost": 413.482282266391,
        "plausibility (FAMD GMM)": 5.308039037081922,
        "plausibility (FAMD Mahalanobis)": 1.3652760950984846,
        "plausibility (SVM)": -2.348439633792443,
        "plausibility (One Class SVM) gamma=scale nu=0.5": 8.269106019530252,
        "plausibility (FAMD One Class SVM) gamma=scale nu=0.5": 0.7305703811687039,
        "wave": 219401.75110778995,
        "combined": 128542976.7161961,
        "compression": 128114853.47122861,
        "tipover": 567316.7768361084,
        "torque": 93675.62437540278
    },
    {
        "id": "c11285",
        "legs": 4,
        "total_height": 23.002602864957353,
        "radius_bottom": 25.254215990286706,
        "radius_top": 8.108877641976232,
        "n_layers": 4,
        "layer_heights": [
            7.445846983469463,
            13.960403394378055
        ],
        "connection_types": [
            "NONE",
            "NONE",
            "NONE"
        ],
        "Cost": 160.62838727773106,
        "plausibility (FAMD GMM)": 2.803577124747331,
        "plausibility (FAMD Mahalanobis)": 0.1772713525044254,
        "plausibility (SVM)": -0.7680083055745874,
        "plausibility (One Class SVM) gamma=scale nu=0.5": 10.041237612267585,
        "plausibility (FAMD One Class SVM) gamma=scale nu=0.5": -0.016870775885179157,
        "wave": 719349.0680143206,
        "combined": 74457952.19313751,
        "compression": 73752719.84090373,
        "tipover": 1357670.2313099334,
        "torque": 1080176.1520605225
    },
    {
        "id": "m2220",
        "legs": 4,
        "total_height": 92.99198459980792,
        "radius_bottom": 23.13559982816389,
        "radius_top": 11.105611817833493,
        "n_layers": 4,
        "layer_heights": [
            7.599296830426529,
            17.42540776314948
        ],
        "connection_types": [
            "K",
            "XH",
            "K"
        ],
        "Cost": 1935.9301941223885,
        "plausibility (FAMD GMM)": 5.370103855155721,
        "plausibility (FAMD Mahalanobis)": 1.8992816079666626,
        "plausibility (SVM)": 1.1247842383087296,
        "plausibility (One Class SVM) gamma=scale nu=0.5": 9.249857811537813,
        "plausibility (FAMD One Class SVM) gamma=scale nu=0.5": 4.953243022894972,
        "wave": 127964.34676117523,
        "combined": 30438057.597892955,
        "compression": 30528803.11252837,
        "tipover": 506038.4627394859,
        "torque": 71982.32912044378
    },
    {
        "id": "c11824",
        "legs": 4,
        "total_height": 50.19097174910359,
        "radius_bottom": 21.564453478914743,
        "radius_top": 11.105611817833493,
        "n_layers": 4,
        "layer_heights": [
            7.599296830426529,
            22.850603188177963
        ],
        "connection_types": [
            "NONE",
            "NONE",
            "NONE"
        ],
        "Cost": 267.8992429776909,
        "plausibility (FAMD GMM)": 5.216572492780738,
        "plausibility (FAMD Mahalanobis)": 0.7169871553432847,
        "plausibility (SVM)": 0.5254679910779836,
        "plausibility (One Class SVM) gamma=scale nu=0.5": 5.313653852676563,
        "plausibility (FAMD One Class SVM) gamma=scale nu=0.5": -0.34914324655675877,
        "wave": 1231954.0334004767,
        "combined": 36694672.44033947,
        "compression": 33201900.464108817,
        "tipover": 3529634.168252647,
        "torque": 1727406.0759982187
    },
    {
        "id": "c10513",
        "legs": 4,
        "total_height": 62.39928906978811,
        "radius_bottom": 19.347582143082285,
        "radius_top": 11.105611817833493,
        "n_layers": 4,
        "layer_heights": [
            22.65485478831501,
            38.21660237209662
        ],
        "connection_types": [
            "K",
            "XH",
            "K"
        ],
        "Cost": 1300.5225552501895,
        "plausibility (FAMD GMM)": 4.61546702310972,
        "plausibility (FAMD Mahalanobis)": 0.2805650892323406,
        "plausibility (SVM)": 0.9813858831079281,
        "plausibility (One Class SVM) gamma=scale nu=0.5": 5.388498550210262,
        "plausibility (FAMD One Class SVM) gamma=scale nu=0.5": -0.47995041958428253,
        "wave": 67701.18922648097,
        "combined": 21206491.120129116,
        "compression": 21131867.944765847,
        "tipover": 348092.1371352594,
        "torque": 95771.96139886095
    },
    {
        "id": "c8840",
        "legs": 4,
        "total_height": 92.99198459980792,
        "radius_bottom": 25.254215990286706,
        "radius_top": 9.658213696306213,
        "n_layers": 4,
        "layer_heights": [
            13.1167717624595,
            13.960403394378055
        ],
        "connection_types": [
            "X",
            "X",
            "XH"
        ],
        "Cost": 1777.3319622676509,
        "plausibility (FAMD GMM)": 5.475746817983986,
        "plausibility (FAMD Mahalanobis)": 1.8707431639820042,
        "plausibility (SVM)": -0.770698261774617,
        "plausibility (One Class SVM) gamma=scale nu=0.5": 6.354587589907574,
        "plausibility (FAMD One Class SVM) gamma=scale nu=0.5": 4.74328064994355,
        "wave": 319731.4423733909,
        "combined": 33720629.06321965,
        "compression": 33341310.03197414,
        "tipover": 445107.8364528744,
        "torque": 60683.97209173881
    },
    {
        "id": "c10210",
        "legs": 4,
        "total_height": 62.39928906978811,
        "radius_bottom": 12.06370949745838,
        "radius_top": 10.585267377739555,
        "n_layers": 4,
        "layer_heights": [
            17.42540776314948,
            22.65485478831501
        ],
        "connection_types": [
            "NONE",
            "Z",
            "NONE"
        ],
        "Cost": 378.36043684025213,
        "plausibility (FAMD GMM)": 4.058253990927534,
        "plausibility (FAMD Mahalanobis)": 0.6455648362440191,
        "plausibility (SVM)": 1.6122494689070614,
        "plausibility (One Class SVM) gamma=scale nu=0.5": 7.782774465935132,
        "plausibility (FAMD One Class SVM) gamma=scale nu=0.5": -0.40359046954740485,
        "wave": 1204544.3950902799,
        "combined": 33041646.16583226,
        "compression": 26702177.390679397,
        "tipover": 5942953.920817226,
        "torque": 1710341.6126854524
    },
    {
        "id": "c10672",
        "legs": 4,
        "total_height": 40.72605377217881,
        "radius_bottom": 21.564453478914743,
        "radius_top": 11.105611817833493,
        "n_layers": 4,
        "layer_heights": [
            8.429072794452487,
            22.850603188177963
        ],
        "connection_types": [
            "NONE",
            "NONE",
            "NONE"
        ],
        "Cost": 231.01313983681038,
        "plausibility (FAMD GMM)": 6.991386740250813,
        "plausibility (FAMD Mahalanobis)": 0.3474638813317408,
        "plausibility (SVM)": 0.3525240973088253,
        "plausibility (One Class SVM) gamma=scale nu=0.5": 6.002239604188324,
        "plausibility (FAMD One Class SVM) gamma=scale nu=0.5": -0.4305464619873902,
        "wave": 1073385.0907201625,
        "combined": 38661134.979794666,
        "compression": 35949724.92162775,
        "tipover": 2916968.620382652,
        "torque": 1591286.6350887427
    },
    {
        "id": "c11606",
        "legs": 3,
        "total_height": 60.01595496362853,
        "radius_bottom": 19.347582143082285,
        "radius_top": 7.100502403895385,
        "n_layers": 4,
        "layer_heights": [
            13.1167717624595,
            17.056259084600164
        ],
        "connection_types": [
            "NONE",
            "NONE",
            "NONE"
        ],
        "Cost": 220.65370022509723,
        "plausibility (FAMD GMM)": 3.5409502875387955,
        "plausibility (FAMD Mahalanobis)": 0.7562308687511492,
        "plausibility (SVM)": 0.22210296002995245,
        "plausibility (One Class SVM) gamma=scale nu=0.5": 6.351948782596372,
        "plausibility (FAMD One Class SVM) gamma=scale nu=0.5": -0.6304180665189136,
        "wave": 1461377.481149935,
        "combined": 47117341.634753816,
        "compression": 42981829.87395547,
        "tipover": 4301412.210202207,
        "torque": 2364834.469524036
    },
    {
        "id": "c11438",
        "legs": 4,
        "total_height": 17.541319641971047,
        "radius_bottom": 22.693572830168364,
        "radius_top": 8.973838804250029,
        "n_layers": 4,
        "layer_heights": [
            13.1167717624595,
            13.960403394378055
        ],
        "connection_types": [
            "NONE",
            "NONE",
            "X"
        ],
        "Cost": 261.6923924478413,
        "plausibility (FAMD GMM)": 5.492393822694265,
        "plausibility (FAMD Mahalanobis)": 1.2611903855548476,
        "plausibility (SVM)": -1.1389020207846463,
        "plausibility (One Class SVM) gamma=scale nu=0.5": 9.145938486531147,
        "plausibility (FAMD One Class SVM) gamma=scale nu=0.5": 0.5967152265299713,
        "wave": 540009.3666647106,
        "combined": 77327731.00116798,
        "compression": 76715861.24113913,
        "tipover": 1134321.6788585847,
        "torque": 830078.5834146786
    },
    {
        "id": "c11816",
        "legs": 4,
        "total_height": 17.541319641971047,
        "radius_bottom": 22.693572830168364,
        "radius_top": 7.100502403895385,
        "n_layers": 4,
        "layer_heights": [
            9.24665220645395,
            13.1167717624595
        ],
        "connection_types": [
            "NONE",
            "NONE",
            "X"
        ],
        "Cost": 244.82124665641263,
        "plausibility (FAMD GMM)": 2.2195864110632804,
        "plausibility (FAMD Mahalanobis)": 0.955397417276079,
        "plausibility (SVM)": -1.3801369823919365,
        "plausibility (One Class SVM) gamma=scale nu=0.5": 9.603497050628608,
        "plausibility (FAMD One Class SVM) gamma=scale nu=0.5": 0.7244301573897349,
        "wave": 505854.1819365072,
        "combined": 86260916.61463968,
        "compression": 85647446.7928933,
        "tipover": 936540.5871041464,
        "torque": 817193.025696165
    },
    {
        "id": "c11774",
        "legs": 3,
        "total_height": 17.541319641971047,
        "radius_bottom": 22.693572830168364,
        "radius_top": 11.105611817833493,
        "n_layers": 4,
        "layer_heights": [
            9.24665220645395,
            17.42540776314948
        ],
        "connection_types": [
            "NONE",
            "X",
            "NONE"
        ],
        "Cost": 274.0359343425901,
        "plausibility (FAMD GMM)": 5.621528739997936,
        "plausibility (FAMD Mahalanobis)": 1.0750965543121538,
        "plausibility (SVM)": -0.9834585250801005,
        "plausibility (One Class SVM) gamma=scale nu=0.5": 9.470339366104083,
        "plausibility (FAMD One Class SVM) gamma=scale nu=0.5": 0.4646898281288987,
        "wave": 533927.7566330212,
        "combined": 90079584.81042176,
        "compression": 89206743.59063093,
        "tipover": 1425792.1075314544,
        "torque": 797153.9520333728
    },
    {
        "id": "c11137",
        "legs": 4,
        "total_height": 17.541319641971047,
        "radius_bottom": 17.109958239742937,
        "radius_top": 7.100502403895385,
        "n_layers": 4,
        "layer_heights": [
            7.445846983469463,
            7.599296830426529
        ],
        "connection_types": [
            "NONE",
            "NONE",
            "NONE"
        ],
        "Cost": 120.95136725497346,
        "plausibility (FAMD GMM)": 7.937784890134861,
        "plausibility (FAMD Mahalanobis)": 0.92019763826502,
        "plausibility (SVM)": -0.2382121436613054,
        "plausibility (One Class SVM) gamma=scale nu=0.5": 8.88735384237635,
        "plausibility (FAMD One Class SVM) gamma=scale nu=0.5": 2.1371810928963964,
        "wave": 641058.1991591303,
        "combined": 60091351.417053476,
        "compression": 59397411.47079069,
        "tipover": 1252432.9755948572,
        "torque": 1140463.9257058422
    },
    {
        "id": "m2287",
        "legs": 4,
        "total_height": 66.82341707458929,
        "radius_bottom": 21.564453478914743,
        "radius_top": 9.606491619540975,
        "n_layers": 4,
        "layer_heights": [
            20.866481762409094,
            49.62334724479272
        ],
        "connection_types": [
            "K",
            "K",
            "K"
        ],
        "Cost": 1208.3664349345117,
        "plausibility (FAMD GMM)": 3.094310961523934,
        "plausibility (FAMD Mahalanobis)": 0.32390453272140773,
        "plausibility (SVM)": 0.6333363788737736,
        "plausibility (One Class SVM) gamma=scale nu=0.5": 5.540024477648275,
        "plausibility (FAMD One Class SVM) gamma=scale nu=0.5": -0.530110941248557,
        "wave": 101920.09222843456,
        "combined": 23534591.63569459,
        "compression": 23562832.905897375,
        "tipover": 318834.6057111091,
        "torque": 86594.12851152243
    },
    {
        "id": "m2050",
        "legs": 3,
        "total_height": 65.21088912804947,
        "radius_bottom": 19.347582143082285,
        "radius_top": 11.105611817833493,
        "n_layers": 4,
        "layer_heights": [
            17.42540776314948,
            48.72579118540414
        ],
        "connection_types": [
            "NONE",
            "X",
            "NONE"
        ],
        "Cost": 500.3648618854185,
        "plausibility (FAMD GMM)": 4.387293572294972,
        "plausibility (FAMD Mahalanobis)": 0.2994643205677663,
        "plausibility (SVM)": 0.1785538011778507,
        "plausibility (One Class SVM) gamma=scale nu=0.5": 2.4995510405168133,
        "plausibility (FAMD One Class SVM) gamma=scale nu=0.5": -0.49700950644971265,
        "wave": 968421.364305933,
        "combined": 48078859.172123305,
        "compression": 44923507.70033428,
        "tipover": 3592669.84409578,
        "torque": 1331220.6772020983
    },
    {
        "id": "m2319",
        "legs": 4,
        "total_height": 65.21088912804947,
        "radius_bottom": 19.347582143082285,
        "radius_top": 11.105611817833493,
        "n_layers": 4,
        "layer_heights": [
            39.17491250952842,
            54.44848154057675
        ],
        "connection_types": [
            "NONE",
            "X",
            "X"
        ],
        "Cost": 679.944053811016,
        "plausibility (FAMD GMM)": 1.1553127588482734,
        "plausibility (FAMD Mahalanobis)": 0.5814293127027534,
        "plausibility (SVM)": -0.36905087773324885,
        "plausibility (One Class SVM) gamma=scale nu=0.5": 0.8194978368620554,
        "plausibility (FAMD One Class SVM) gamma=scale nu=0.5": -0.04693846049619843,
        "wave": 929779.5208811963,
        "combined": 32717259.21482558,
        "compression": 28996172.973684136,
        "tipover": 3226127.945506186,
        "torque": 1691385.7200423677
    },
    {
        "id": "c11771",
        "legs": 3,
        "total_height": 42.83293090534487,
        "radius_bottom": 12.131531614719336,
        "radius_top": 8.759208300635935,
        "n_layers": 4,
        "layer_heights": [
            7.599296830426529,
            9.24665220645395
        ],
        "connection_types": [
            "NONE",
            "NONE",
            "NONE"
        ],
        "Cost": 174.4106236264176,
        "plausibility (FAMD GMM)": 2.6762580914671075,
        "plausibility (FAMD Mahalanobis)": 1.0096966312109905,
        "plausibility (SVM)": 0.775895253113442,
        "plausibility (One Class SVM) gamma=scale nu=0.5": 8.703820346642937,
        "plausibility (FAMD One Class SVM) gamma=scale nu=0.5": -0.4763115513315075,
        "wave": 1416927.457717314,
        "combined": 43071154.19323042,
        "compression": 37443826.10954086,
        "tipover": 5352526.992967293,
        "torque": 2527992.2501791078
    },
    {
        "id": "c11463",
        "legs": 3,
        "total_height": 53.22186980872247,
        "radius_bottom": 21.564453478914743,
        "radius_top": 11.105611817833493,
        "n_layers": 4,
        "layer_heights": [
            17.42540776314948,
            49.62334724479272
        ],
        "connection_types": [
            "NONE",
            "NONE",
            "X"
        ],
        "Cost": 341.4732916802671,
        "plausibility (FAMD GMM)": 0.580151970971145,
        "plausibility (FAMD Mahalanobis)": 0.38262118203719464,
        "plausibility (SVM)": -0.180363704371151,
        "plausibility (One Class SVM) gamma=scale nu=0.5": 4.708402810580072,
        "plausibility (FAMD One Class SVM) gamma=scale nu=0.5": -0.3090122303129377,
        "wave": 1291948.385367776,
        "combined": 47010960.77646911,
        "compression": 42404678.39391331,
        "tipover": 4975539.489186903,
        "torque": 2325122.4519196795
    },
    {
        "id": "c10911",
        "legs": 4,
        "total_height": 23.002602864957353,
        "radius_bottom": 19.347582143082285,
        "radius_top": 7.100502403895385,
        "n_layers": 4,
        "layer_heights": [
            13.1167717624595,
            17.056259084600164
        ],
        "connection_types": [
            "NONE",
            "X",
            "X"
        ],
        "Cost": 387.39075576116056,
        "plausibility (FAMD GMM)": 2.6402313272274154,
        "plausibility (FAMD Mahalanobis)": 1.1132975366301978,
        "plausibility (SVM)": -1.6553244735422843,
        "plausibility (One Class SVM) gamma=scale nu=0.5": 5.518323189677563,
        "plausibility (FAMD One Class SVM) gamma=scale nu=0.5": 1.186093974950035,
        "wave": 423354.4023775971,
        "combined": 56888699.65167649,
        "compression": 56587639.03319305,
        "tipover": 948157.3296184661,
        "torque": 843528.3972567368
    },
    {
        "id": "c11787",
        "legs": 3,
        "total_height": 17.541319641971047,
        "radius_bottom": 19.347582143082285,
        "radius_top": 11.105611817833493,
        "n_layers": 4,
        "layer_heights": [
            13.960403394378055,
            17.42540776314948
        ],
        "connection_types": [
            "NONE",
            "X",
            "NONE"
        ],
        "Cost": 242.10766199620295,
        "plausibility (FAMD GMM)": 2.964888661655843,
        "plausibility (FAMD Mahalanobis)": 1.6313031111187304,
        "plausibility (SVM)": -0.6944958006437694,
        "plausibility (One Class SVM) gamma=scale nu=0.5": 8.874445985411203,
        "plausibility (FAMD One Class SVM) gamma=scale nu=0.5": 1.1578135496376714,
        "wave": 646494.6401552476,
        "combined": 69030778.1418073,
        "compression": 67760404.70867765,
        "tipover": 1956635.522056279,
        "torque": 1200390.836486652
    },
    {
        "id": "c10884",
        "legs": 4,
        "total_height": 87.37244929648898,
        "radius_bottom": 22.54138231115348,
        "radius_top": 11.105611817833493,
        "n_layers": 4,
        "layer_heights": [
            13.1167717624595,
            22.850603188177963
        ],
        "connection_types": [
            "XH",
            "XH",
            "XH"
        ],
        "Cost": 1826.2284265750206,
        "plausibility (FAMD GMM)": 4.950020629928858,
        "plausibility (FAMD Mahalanobis)": 1.5840219575171266,
        "plausibility (SVM)": 1.2589242943315875,
        "plausibility (One Class SVM) gamma=scale nu=0.5": 8.23560602029956,
        "plausibility (FAMD One Class SVM) gamma=scale nu=0.5": 2.850724324645622,
        "wave": 128354.55470298139,
        "combined": 31813171.32177469,
        "compression": 31195447.60269037,
        "tipover": 488051.1628203668,
        "torque": 69674.6119571559
    },
    {
        "id": "c11583",
        "legs": 3,
        "total_height": 65.21088912804947,
        "radius_bottom": 19.347582143082285,
        "radius_top": 11.105611817833493,
        "n_layers": 4,
        "layer_heights": [
            7.445846983469463,
            48.72579118540414
        ],
        "connection_types": [
            "X",
            "NONE",
            "X"
        ],
        "Cost": 616.6091896461724,
        "plausibility (FAMD GMM)": 6.804000099560819,
        "plausibility (FAMD Mahalanobis)": 0.49611334455786366,
        "plausibility (SVM)": -0.5424245576748965,
        "plausibility (One Class SVM) gamma=scale nu=0.5": 1.3061190688954554,
        "plausibility (FAMD One Class SVM) gamma=scale nu=0.5": -0.46922645665353,
        "wave": 455802.0558147853,
        "combined": 39888619.49235263,
        "compression": 38763810.73604821,
        "tipover": 2289000.9489180674,
        "torque": 460573.8464948476
    },
    {
        "id": "c11811",
        "legs": 4,
        "total_height": 44.438895795085756,
        "radius_bottom": 21.564453478914743,
        "radius_top": 11.105611817833493,
        "n_layers": 4,
        "layer_heights": [
            7.445846983469463,
            8.429072794452487
        ],
        "connection_types": [
            "X",
            "X",
            "X"
        ],
        "Cost": 1049.8771530542033,
        "plausibility (FAMD GMM)": 3.658186451531178,
        "plausibility (FAMD Mahalanobis)": 0.9881044213814226,
        "plausibility (SVM)": -1.6813189632172985,
        "plausibility (One Class SVM) gamma=scale nu=0.5": -0.7923068657153678,
        "plausibility (FAMD One Class SVM) gamma=scale nu=0.5": -0.08317489717939175,
        "wave": 161177.1191579369,
        "combined": 35787078.224699,
        "compression": 35998641.696345836,
        "tipover": 366340.4921199697,
        "torque": 82926.59811757867
    },
    {
        "id": "c11127",
        "legs": 3,
        "total_height": 62.39928906978811,
        "radius_bottom": 21.564453478914743,
        "radius_top": 11.105611817833493,
        "n_layers": 4,
        "layer_heights": [
            14.848844498073804,
            20.071651715087423
        ],
        "connection_types": [
            "NONE",
            "NONE",
            "NONE"
        ],
        "Cost": 247.51563964365886,
        "plausibility (FAMD GMM)": 4.943969155889692,
        "plausibility (FAMD Mahalanobis)": 0.9413638756335759,
        "plausibility (SVM)": 0.6180901389319708,
        "plausibility (One Class SVM) gamma=scale nu=0.5": 5.479151835114367,
        "plausibility (FAMD One Class SVM) gamma=scale nu=0.5": 0.05122960695017653,
        "wave": 1714490.6672711202,
        "combined": 47041323.44051351,
        "compression": 41523387.705951974,
        "tipover": 5856244.453437536,
        "torque": 2417420.186635695
    },
    {
        "id": "c11750",
        "legs": 3,
        "total_height": 53.22186980872247,
        "radius_bottom": 19.347582143082285,
        "radius_top": 10.10748640842396,
        "n_layers": 4,
        "layer_heights": [
            38.56816390611271,
            42.055444030465864
        ],
        "connection_types": [
            "NONE",
            "X",
            "NONE"
        ],
        "Cost": 344.6144719608671,
        "plausibility (FAMD GMM)": 3.109387937606827,
        "plausibility (FAMD Mahalanobis)": 0.8316680575008755,
        "plausibility (SVM)": -0.2065054636458732,
        "plausibility (One Class SVM) gamma=scale nu=0.5": 2.661061390248026,
        "plausibility (FAMD One Class SVM) gamma=scale nu=0.5": 0.2522524910450503,
        "wave": 1124251.1730983884,
        "combined": 45168754.281351626,
        "compression": 41623835.72827581,
        "tipover": 4308092.727937677,
        "torque": 2221878.5913542924
    },
    {
        "id": "c11785",
        "legs": 3,
        "total_height": 41.15076949031787,
        "radius_bottom": 17.109958239742937,
        "radius_top": 7.100502403895385,
        "n_layers": 4,
        "layer_heights": [
            7.445846983469463,
            40.878847930028684
        ],
        "connection_types": [
            "NONE",
            "NONE",
            "NONE"
        ],
        "Cost": 163.9471535260626,
        "plausibility (FAMD GMM)": 3.6070175531611164,
        "plausibility (FAMD Mahalanobis)": 0.7633233091372921,
        "plausibility (SVM)": 0.09736694377120125,
        "plausibility (One Class SVM) gamma=scale nu=0.5": 7.229376075227746,
        "plausibility (FAMD One Class SVM) gamma=scale nu=0.5": 1.2921560089737394,
        "wave": 1169696.5600315891,
        "combined": 49089141.9573324,
        "compression": 45892399.81971841,
        "tipover": 3370331.204157779,
        "torque": 2313496.6610082667
    },
    {
        "id": "c11736",
        "legs": 4,
        "total_height": 23.002602864957353,
        "radius_bottom": 19.347582143082285,
        "radius_top": 4.97754914857337,
        "n_layers": 4,
        "layer_heights": [
            13.1167717624595,
            13.960403394378055
        ],
        "connection_types": [
            "NONE",
            "X",
            "IZH"
        ],
        "Cost": 379.4394625260026,
        "plausibility (FAMD GMM)": 3.0422517109855485,
        "plausibility (FAMD Mahalanobis)": 1.1358568673641352,
        "plausibility (SVM)": -1.2799867943960144,
        "plausibility (One Class SVM) gamma=scale nu=0.5": 8.594849435205537,
        "plausibility (FAMD One Class SVM) gamma=scale nu=0.5": 1.920425580917252,
        "wave": 404139.9718434795,
        "combined": 64082617.56177353,
        "compression": 64143151.35056166,
        "tipover": 799468.9190750961,
        "torque": 897422.4521973515
    },
    {
        "id": "c10199",
        "legs": 4,
        "total_height": 92.99198459980792,
        "radius_bottom": 25.254215990286706,
        "radius_top": 11.105611817833493,
        "n_layers": 4,
        "layer_heights": [
            7.599296830426529,
            17.42540776314948
        ],
        "connection_types": [
            "K",
            "XH",
            "K"
        ],
        "Cost": 2010.3927532756454,
        "plausibility (FAMD GMM)": 6.043712639808678,
        "plausibility (FAMD Mahalanobis)": 2.017001820084449,
        "plausibility (SVM)": 0.8953950268771913,
        "plausibility (One Class SVM) gamma=scale nu=0.5": 9.907042313334314,
        "plausibility (FAMD One Class SVM) gamma=scale nu=0.5": 5.757740086196243,
        "wave": 124445.34235412678,
        "combined": 31140538.684134144,
        "compression": 31150059.74651659,
        "tipover": 469279.72802646505,
        "torque": 66095.05547547666
    },
    {
        "id": "c11487",
        "legs": 3,
        "total_height": 17.541319641971047,
        "radius_bottom": 22.166202051151185,
        "radius_top": 8.973838804250029,
        "n_layers": 4,
        "layer_heights": [
            9.355444817438064,
            17.42540776314948
        ],
        "connection_types": [
            "NONE",
            "NONE",
            "NONE"
        ],
        "Cost": 112.47491309667511,
        "plausibility (FAMD GMM)": 5.51062283017554,
        "plausibility (FAMD Mahalanobis)": 1.206761956306434,
        "plausibility (SVM)": -0.5543180956593452,
        "plausibility (One Class SVM) gamma=scale nu=0.5": 10.595498496588437,
        "plausibility (FAMD One Class SVM) gamma=scale nu=0.5": 0.5665110878146606,
        "wave": 782234.1989605788,
        "combined": 100166870.17688155,
        "compression": 99309578.9591865,
        "tipover": 1777153.6809017765,
        "torque": 1279908.068168769
    },
    {
        "id": "c11853",
        "legs": 4,
        "total_height": 64.92824710519619,
        "radius_bottom": 15.26770338779989,
        "radius_top": 12.06370949745838,
        "n_layers": 4,
        "layer_heights": [
            42.15696043499321,
            59.56832484710567
        ],
        "connection_types": [
            "NONE",
            "K",
            "NONE"
        ],
        "Cost": 558.7204117135562,
        "plausibility (FAMD GMM)": 2.4954505812338814,
        "plausibility (FAMD Mahalanobis)": 0.7761120704299224,
        "plausibility (SVM)": 1.5793948324614697,
        "plausibility (One Class SVM) gamma=scale nu=0.5": 6.77984359111931,
        "plausibility (FAMD One Class SVM) gamma=scale nu=0.5": 0.1973146619104984,
        "wave": 1079852.5662930072,
        "combined": 31992690.050659694,
        "compression": 26746052.567381322,
        "tipover": 4467159.797673673,
        "torque": 1877648.4054021293
    },
    {
        "id": "c11845",
        "legs": 3,
        "total_height": 44.438895795085756,
        "radius_bottom": 19.347582143082285,
        "radius_top": 8.973838804250029,
        "n_layers": 4,
        "layer_heights": [
            17.056259084600164,
            39.17491250952842
        ],
        "connection_types": [
            "NONE",
            "X",
            "X"
        ],
        "Cost": 476.5496394172783,
        "plausibility (FAMD GMM)": 1.2924563170431818,
        "plausibility (FAMD Mahalanobis)": 0.5525244504313741,
        "plausibility (SVM)": -1.117847509570273,
        "plausibility (One Class SVM) gamma=scale nu=0.5": 2.6400482944038473,
        "plausibility (FAMD One Class SVM) gamma=scale nu=0.5": 0.28975936539984914,
        "wave": 715275.4356519508,
        "combined": 57971194.57933507,
        "compression": 56284867.379452534,
        "tipover": 2234202.704339946,
        "torque": 1400088.3909898817
    },
    {
        "id": "c11671",
        "legs": 3,
        "total_height": 44.438895795085756,
        "radius_bottom": 22.693572830168364,
        "radius_top": 11.105611817833493,
        "n_layers": 4,
        "layer_heights": [
            17.056259084600164,
            22.65485478831501
        ],
        "connection_types": [
            "Z",
            "Z",
            "Z"
        ],
        "Cost": 504.2321791927545,
        "plausibility (FAMD GMM)": 4.058562336543246,
        "plausibility (FAMD Mahalanobis)": 0.3053055194680794,
        "plausibility (SVM)": 0.37475009304606965,
        "plausibility (One Class SVM) gamma=scale nu=0.5": 7.514544470474835,
        "plausibility (FAMD One Class SVM) gamma=scale nu=0.5": -0.5066623190508768,
        "wave": 321204.2082412129,
        "combined": 53270935.47050778,
        "compression": 53247938.503334105,
        "tipover": 1213760.7843242332,
        "torque": 352534.13838951034
    },
    {
        "id": "c10843",
        "legs": 4,
        "total_height": 66.82341707458929,
        "radius_bottom": 15.26770338779989,
        "radius_top": 12.06370949745838,
        "n_layers": 5,
        "layer_heights": [
            38.21660237209662,
            58.135647727091126,
            59.56832484710567
        ],
        "connection_types": [
            "K",
            "X",
            "X",
            "X"
        ],
        "Cost": 1245.4306971804995,
        "plausibility (FAMD GMM)": 1.4465429011736888,
        "plausibility (FAMD Mahalanobis)": 0.45753787496687454,
        "plausibility (SVM)": -0.3055702056734808,
        "plausibility (One Class SVM) gamma=scale nu=0.5": 3.9362690557400075,
        "plausibility (FAMD One Class SVM) gamma=scale nu=0.5": 0.22646696868825167,
        "wave": 122526.76649132806,
        "combined": 22928410.228230808,
        "compression": 23965107.847845133,
        "tipover": 541884.7442670384,
        "torque": 124962.05262885602
    },
    {
        "id": "c11524",
        "legs": 4,
        "total_height": 62.39928906978811,
        "radius_bottom": 21.564453478914743,
        "radius_top": 11.105611817833493,
        "n_layers": 4,
        "layer_heights": [
            17.056259084600164,
            19.09548147893374
        ],
        "connection_types": [
            "X",
            "X",
            "NONE"
        ],
        "Cost": 792.2744123217786,
        "plausibility (FAMD GMM)": 5.13932746964022,
        "plausibility (FAMD Mahalanobis)": 0.9082224586686838,
        "plausibility (SVM)": -0.75941229137158,
        "plausibility (One Class SVM) gamma=scale nu=0.5": -0.3872001082713403,
        "plausibility (FAMD One Class SVM) gamma=scale nu=0.5": -0.017216605443747923,
        "wave": 203290.3502871324,
        "combined": 36677835.16612383,
        "compression": 36716409.48279426,
        "tipover": 684525.6808782655,
        "torque": 198216.69701158602
    },
    {
        "id": "c11591",
        "legs": 3,
        "total_height": 65.21088912804947,
        "radius_bottom": 19.347582143082285,
        "radius_top": 8.973838804250029,
        "n_layers": 4,
        "layer_heights": [
            17.42540776314948,
            48.72579118540414
        ],
        "connection_types": [
            "NONE",
            "X",
            "NONE"
        ],
        "Cost": 483.30419545420864,
        "plausibility (FAMD GMM)": 5.0377128494823324,
        "plausibility (FAMD Mahalanobis)": 0.11644699432691463,
        "plausibility (SVM)": -0.1259238806979588,
        "plausibility (One Class SVM) gamma=scale nu=0.5": 2.4758587117153255,
        "plausibility (FAMD One Class SVM) gamma=scale nu=0.5": -0.3117330476854665,
        "wave": 906218.6793322449,
        "combined": 50568530.99929643,
        "compression": 47925074.93622809,
        "tipover": 3132503.2247303464,
        "torque": 1343565.265850917
    },
    {
        "id": "c11352",
        "legs": 4,
        "total_height": 62.39928906978811,
        "radius_bottom": 21.564453478914743,
        "radius_top": 8.973838804250029,
        "n_layers": 4,
        "layer_heights": [
            19.09548147893374,
            39.17491250952842
        ],
        "connection_types": [
            "X",
            "X",
            "X"
        ],
        "Cost": 1043.5534005891489,
        "plausibility (FAMD GMM)": 5.580412631786702,
        "plausibility (FAMD Mahalanobis)": 0.29720629843988916,
        "plausibility (SVM)": -1.6992558619190894,
        "plausibility (One Class SVM) gamma=scale nu=0.5": -2.697189417387552,
        "plausibility (FAMD One Class SVM) gamma=scale nu=0.5": -0.4684187423211785,
        "wave": 91937.94873404659,
        "combined": 35609118.78811798,
        "compression": 35355563.16326143,
        "tipover": 406610.55740977253,
        "torque": 66660.74791086862
    },
    {
        "id": "c11793",
        "legs": 3,
        "total_height": 17.541319641971047,
        "radius_bottom": 19.347582143082285,
        "radius_top": 7.100502403895385,
        "n_layers": 4,
        "layer_heights": [
            9.355444817438064,
            13.1167717624595
        ],
        "connection_types": [
            "X",
            "X",
            "NONE"
        ],
        "Cost": 400.36847968266903,
        "plausibility (FAMD GMM)": 2.7439261829398083,
        "plausibility (FAMD Mahalanobis)": 1.1577572660760187,
        "plausibility (SVM)": -2.0187599823787443,
        "plausibility (One Class SVM) gamma=scale nu=0.5": 7.083173456533748,
        "plausibility (FAMD One Class SVM) gamma=scale nu=0.5": 1.406877966660602,
        "wave": 143591.06605791245,
        "combined": 98800065.41697635,
        "compression": 98427092.96083973,
        "tipover": 567492.1641937715,
        "torque": 144165.78208219353
    },
    {
        "id": "c10944",
        "legs": 3,
        "total_height": 60.01595496362853,
        "radius_bottom": 22.693572830168364,
        "radius_top": 8.973838804250029,
        "n_layers": 4,
        "layer_heights": [
            17.42540776314948,
            59.61937350675456
        ],
        "connection_types": [
            "NONE",
            "NONE",
            "NONE"
        ],
        "Cost": 231.3219180307714,
        "plausibility (FAMD GMM)": 0.6179689586843039,
        "plausibility (FAMD Mahalanobis)": 0.36778456733874043,
        "plausibility (SVM)": 0.14845367611669724,
        "plausibility (One Class SVM) gamma=scale nu=0.5": 5.843663820818188,
        "plausibility (FAMD One Class SVM) gamma=scale nu=0.5": -0.29901281231810906,
        "wave": 1522528.8947748838,
        "combined": 49219659.6672304,
        "compression": 45029798.021087475,
        "tipover": 4552072.699930305,
        "torque": 2346720.7496226146
    },
    {
        "id": "c11245",
        "legs": 4,
        "total_height": 40.72605377217881,
        "radius_bottom": 22.693572830168364,
        "radius_top": 11.105611817833493,
        "n_layers": 4,
        "layer_heights": [
            8.429072794452487,
            13.1167717624595
        ],
        "connection_types": [
            "NONE",
            "NONE",
            "NONE"
        ],
        "Cost": 232.1930631030677,
        "plausibility (FAMD GMM)": 5.023249403350161,
        "plausibility (FAMD Mahalanobis)": 0.727537666073432,
        "plausibility (SVM)": 0.24252456108880915,
        "plausibility (One Class SVM) gamma=scale nu=0.5": 6.55544988237852,
        "plausibility (FAMD One Class SVM) gamma=scale nu=0.5": -0.35081638588434316,
        "wave": 1060650.1809468765,
        "combined": 40089254.55133238,
        "compression": 37567418.99289809,
        "tipover": 2813512.852971621,
        "torque": 1555832.4813373808
    },
    {
        "id": "c11495",
        "legs": 4,
        "total_height": 87.37244929648898,
        "radius_bottom": 22.693572830168364,
        "radius_top": 9.316306956374623,
        "n_layers": 4,
        "layer_heights": [
            13.1167717624595,
            13.960403394378055
        ],
        "connection_types": [
            "X",
            "X",
            "X"
        ],
        "Cost": 1521.2063589850547,
        "plausibility (FAMD GMM)": 4.3563513807988175,
        "plausibility (FAMD Mahalanobis)": 1.6009688215132714,
        "plausibility (SVM)": -1.3352536440210847,
        "plausibility (One Class SVM) gamma=scale nu=0.5": 1.7935681967997112,
        "plausibility (FAMD One Class SVM) gamma=scale nu=0.5": 2.8949342267557086,
        "wave": 319024.476197605,
        "combined": 33282228.386687793,
        "compression": 32941789.137945194,
        "tipover": 455847.0564684875,
        "torque": 68854.07774439183
    },
    {
        "id": "c11257",
        "legs": 4,
        "total_height": 66.82341707458929,
        "radius_bottom": 15.26770338779989,
        "radius_top": 12.06370949745838,
        "n_layers": 5,
        "layer_heights": [
            22.850603188177963,
            38.21660237209662,
            59.56832484710567
        ],
        "connection_types": [
            "K",
            "XH",
            "XH",
            "X"
        ],
        "Cost": 1422.1504166602963,
        "plausibility (FAMD GMM)": 5.452710763168501,
        "plausibility (FAMD Mahalanobis)": 0.4410123123554586,
        "plausibility (SVM)": 1.2334559075817517,
        "plausibility (One Class SVM) gamma=scale nu=0.5": 7.951681804597451,
        "plausibility (FAMD One Class SVM) gamma=scale nu=0.5": -0.3167127834561505,
        "wave": 76051.68692263516,
        "combined": 18790321.01632372,
        "compression": 18490141.53933831,
        "tipover": 470094.20423346723,
        "torque": 121187.35717343031
    },
    {
        "id": "m2306",
        "legs": 4,
        "total_height": 40.72605377217881,
        "radius_bottom": 22.54138231115348,
        "radius_top": 11.105611817833493,
        "n_layers": 4,
        "layer_heights": [
            8.429072794452487,
            38.21660237209662
        ],
        "connection_types": [
            "NONE",
            "NONE",
            "X"
        ],
        "Cost": 363.2650757697489,
        "plausibility (FAMD GMM)": 1.0646466031003419,
        "plausibility (FAMD Mahalanobis)": 0.2636639001910244,
        "plausibility (SVM)": -0.371499622250814,
        "plausibility (One Class SVM) gamma=scale nu=0.5": 5.397150348225926,
        "plausibility (FAMD One Class SVM) gamma=scale nu=0.5": -0.31488131809062203,
        "wave": 912050.4392865966,
        "combined": 39476448.047455356,
        "compression": 36883825.60803382,
        "tipover": 2751927.9296547766,
        "torque": 1538914.604766853
    },
    {
        "id": "c11258",
        "legs": 4,
        "total_height": 23.002602864957353,
        "radius_bottom": 25.254215990286706,
        "radius_top": 8.973838804250029,
        "n_layers": 4,
        "layer_heights": [
            13.960403394378055,
            20.071651715087423
        ],
        "connection_types": [
            "NONE",
            "NONE",
            "NONE"
        ],
        "Cost": 163.48781590458785,
        "plausibility (FAMD GMM)": 5.139365338347617,
        "plausibility (FAMD Mahalanobis)": 0.9951226479329938,
        "plausibility (SVM)": -0.675957568561818,
        "plausibility (One Class SVM) gamma=scale nu=0.5": 9.875800694687648,
        "plausibility (FAMD One Class SVM) gamma=scale nu=0.5": 0.42284950716885383,
        "wave": 737659.4971505352,
        "combined": 71260733.98183006,
        "compression": 70431590.0541366,
        "tipover": 1460461.8587655984,
        "torque": 1068893.659741498
    },
    {
        "id": "m2133",
        "legs": 3,
        "total_height": 64.41636347109878,
        "radius_bottom": 22.693572830168364,
        "radius_top": 10.10748640842396,
        "n_layers": 4,
        "layer_heights": [
            9.54555281480225,
            33.04345586904532
        ],
        "connection_types": [
            "X",
            "NONE",
            "NONE"
        ],
        "Cost": 482.7774460121936,
        "plausibility (FAMD GMM)": 5.574782571630226,
        "plausibility (FAMD Mahalanobis)": 0.8454322764401799,
        "plausibility (SVM)": -0.39013325355033635,
        "plausibility (One Class SVM) gamma=scale nu=0.5": 3.1509625078871473,
        "plausibility (FAMD One Class SVM) gamma=scale nu=0.5": -0.13653021562097223,
        "wave": 539993.521973627,
        "combined": 44543707.39060278,
        "compression": 42572318.24280294,
        "tipover": 2369385.600452589,
        "torque": 638375.1996289166
    },
    {
        "id": "c11835",
        "legs": 4,
        "total_height": 62.39928906978811,
        "radius_bottom": 19.347582143082285,
        "radius_top": 8.973838804250029,
        "n_layers": 4,
        "layer_heights": [
            17.056259084600164,
            38.21660237209662
        ],
        "connection_types": [
            "XH",
            "K",
            "XH"
        ],
        "Cost": 1335.2315068213234,
        "plausibility (FAMD GMM)": 7.053766692973717,
        "plausibility (FAMD Mahalanobis)": 0.25930731186304934,
        "plausibility (SVM)": 0.857276937308479,
        "plausibility (One Class SVM) gamma=scale nu=0.5": 5.210480781185051,
        "plausibility (FAMD One Class SVM) gamma=scale nu=0.5": -0.34624780295326296,
        "wave": 83408.09863800234,
        "combined": 36594761.34504707,
        "compression": 36075899.07037492,
        "tipover": 432375.9318932537,
        "torque": 74422.80806181162
    },
    {
        "id": "c11281",
        "legs": 4,
        "total_height": 64.92824710519619,
        "radius_bottom": 15.26770338779989,
        "radius_top": 12.06370949745838,
        "n_layers": 4,
        "layer_heights": [
            16.52011732246095,
            28.106538611637923
        ],
        "connection_types": [
            "NONE",
            "K",
            "NONE"
        ],
        "Cost": 531.549910408709,
        "plausibility (FAMD GMM)": 4.866701512723419,
        "plausibility (FAMD Mahalanobis)": 0.6006711903191801,
        "plausibility (SVM)": 1.6201443618903064,
        "plausibility (One Class SVM) gamma=scale nu=0.5": 6.766091216922932,
        "plausibility (FAMD One Class SVM) gamma=scale nu=0.5": -0.47469619493334925,
        "wave": 596723.5277302547,
        "combined": 29130004.9099948,
        "compression": 27440563.96271245,
        "tipover": 1910938.8928179091,
        "torque": 1008227.6823792094
    },
    {
        "id": "c9525",
        "legs": 3,
        "total_height": 17.541319641971047,
        "radius_bottom": 22.693572830168364,
        "radius_top": 7.100502403895385,
        "n_layers": 4,
        "layer_heights": [
            9.355444817438064,
            13.1167717624595
        ],
        "connection_types": [
            "X",
            "NONE",
            "NONE"
        ],
        "Cost": 309.4881326898234,
        "plausibility (FAMD GMM)": 2.274553409628509,
        "plausibility (FAMD Mahalanobis)": 0.9647006971769769,
        "plausibility (SVM)": -1.6481623989526972,
        "plausibility (One Class SVM) gamma=scale nu=0.5": 9.866007670777964,
        "plausibility (FAMD One Class SVM) gamma=scale nu=0.5": 0.7207532393752984,
        "wave": 178003.76785807003,
        "combined": 117817999.48346433,
        "compression": 117270414.17093295,
        "tipover": 650379.5438968476,
        "torque": 175122.2797531665
    },
    {
        "id": "c11652",
        "legs": 3,
        "total_height": 62.39928906978811,
        "radius_bottom": 19.347582143082285,
        "radius_top": 8.973838804250029,
        "n_layers": 4,
        "layer_heights": [
            17.42540776314948,
            19.09548147893374
        ],
        "connection_types": [
            "X",
            "X",
            "X"
        ],
        "Cost": 911.4015469981593,
        "plausibility (FAMD GMM)": 4.399688133218369,
        "plausibility (FAMD Mahalanobis)": 0.6923470973066573,
        "plausibility (SVM)": -1.6002610050986923,
        "plausibility (One Class SVM) gamma=scale nu=0.5": -1.791146638975814,
        "plausibility (FAMD One Class SVM) gamma=scale nu=0.5": -0.47560653037762535,
        "wave": 233454.39992781196,
        "combined": 48618571.97748608,
        "compression": 48026496.10513729,
        "tipover": 768404.4914921145,
        "torque": 106870.31404029261
    },
    {
        "id": "m1979",
        "legs": 4,
        "total_height": 23.002602864957353,
        "radius_bottom": 27.884824335003138,
        "radius_top": 8.973838804250029,
        "n_layers": 4,
        "layer_heights": [
            19.09548147893374,
            20.071651715087423
        ],
        "connection_types": [
            "X",
            "X",
            "X"
        ],
        "Cost": 709.2304502157193,
        "plausibility (FAMD GMM)": 4.068443731380215,
        "plausibility (FAMD Mahalanobis)": 1.341424296583461,
        "plausibility (SVM)": -3.022174548636945,
        "plausibility (One Class SVM) gamma=scale nu=0.5": 7.9801126969480745,
        "plausibility (FAMD One Class SVM) gamma=scale nu=0.5": 1.5139406452098925,
        "wave": 267344.2896225431,
        "combined": 89747861.6060417,
        "compression": 89429381.36372836,
        "tipover": 291338.5539006864,
        "torque": 49559.45525648655
    },
    {
        "id": "c11783",
        "legs": 4,
        "total_height": 62.39928906978811,
        "radius_bottom": 18.92039882124778,
        "radius_top": 11.105611817833493,
        "n_layers": 4,
        "layer_heights": [
            9.24665220645395,
            54.44848154057675
        ],
        "connection_types": [
            "X",
            "NONE",
            "NONE"
        ],
        "Cost": 534.7670473036227,
        "plausibility (FAMD GMM)": 4.847722153079777,
        "plausibility (FAMD Mahalanobis)": 0.2279532431747007,
        "plausibility (SVM)": 0.19346376922708908,
        "plausibility (One Class SVM) gamma=scale nu=0.5": 2.2694428565379923,
        "plausibility (FAMD One Class SVM) gamma=scale nu=0.5": -0.4345798614751235,
        "wave": 414075.8262791824,
        "combined": 31729152.70346917,
        "compression": 30798845.425983533,
        "tipover": 1642149.0910764167,
        "torque": 589154.8554879382
    },
    {
        "id": "c11763",
        "legs": 3,
        "total_height": 33.61194778792329,
        "radius_bottom": 21.564453478914743,
        "radius_top": 7.100502403895385,
        "n_layers": 4,
        "layer_heights": [
            19.09548147893374,
            19.396398256879653
        ],
        "connection_types": [
            "X",
            "X",
            "X"
        ],
        "Cost": 637.6497157055991,
        "plausibility (FAMD GMM)": 1.6347141229819142,
        "plausibility (FAMD Mahalanobis)": 0.6099673881362341,
        "plausibility (SVM)": -2.576672968404798,
        "plausibility (One Class SVM) gamma=scale nu=0.5": 3.729387822704247,
        "plausibility (FAMD One Class SVM) gamma=scale nu=0.5": 0.5054432840282814,
        "wave": 114711.81546777903,
        "combined": 75542477.01760514,
        "compression": 75089720.89713578,
        "tipover": 610021.7322661692,
        "torque": 94515.92484849555
    },
    {
        "id": "c11316",
        "legs": 3,
        "total_height": 17.541319641971047,
        "radius_bottom": 21.564453478914743,
        "radius_top": 11.105611817833493,
        "n_layers": 4,
        "layer_heights": [
            9.24665220645395,
            14.848844498073804
        ],
        "connection_types": [
            "NONE",
            "X",
            "NONE"
        ],
        "Cost": 272.4879425210666,
        "plausibility (FAMD GMM)": 2.887253557023292,
        "plausibility (FAMD Mahalanobis)": 0.8974269485302728,
        "plausibility (SVM)": -0.8736082005874173,
        "plausibility (One Class SVM) gamma=scale nu=0.5": 9.093998349529384,
        "plausibility (FAMD One Class SVM) gamma=scale nu=0.5": 0.3326376104587876,
        "wave": 519666.65053097357,
        "combined": 82453095.88487116,
        "compression": 82179606.35028517,
        "tipover": 1445079.0495155049,
        "torque": 809456.5263274978
    },
    {
        "id": "c11586",
        "legs": 4,
        "total_height": 23.002602864957353,
        "radius_bottom": 22.693572830168364,
        "radius_top": 10.10748640842396,
        "n_layers": 4,
        "layer_heights": [
            19.09548147893374,
            20.071651715087423
        ],
        "connection_types": [
            "X",
            "X",
            "X"
        ],
        "Cost": 680.4930746447652,
        "plausibility (FAMD GMM)": 3.907209828342186,
        "plausibility (FAMD Mahalanobis)": 1.3923277575531356,
        "plausibility (SVM)": -2.3612943678298612,
        "plausibility (One Class SVM) gamma=scale nu=0.5": 3.869423062102145,
        "plausibility (FAMD One Class SVM) gamma=scale nu=0.5": 0.9655014190549753,
        "wave": 257831.28940675274,
        "combined": 65888953.09884338,
        "compression": 65548406.90602472,
        "tipover": 286704.3485916041,
        "torque": 60411.7925220603
    },
    {
        "id": "c11666",
        "legs": 3,
        "total_height": 17.541319641971047,
        "radius_bottom": 19.347582143082285,
        "radius_top": 10.10748640842396,
        "n_layers": 4,
        "layer_heights": [
            13.960403394378055,
            17.42540776314948
        ],
        "connection_types": [
            "X",
            "K",
            "X"
        ],
        "Cost": 521.1807272173969,
        "plausibility (FAMD GMM)": 2.8988995451913886,
        "plausibility (FAMD Mahalanobis)": 1.6840946501590695,
        "plausibility (SVM)": -1.4239476130658537,
        "plausibility (One Class SVM) gamma=scale nu=0.5": 8.346987073598905,
        "plausibility (FAMD One Class SVM) gamma=scale nu=0.5": 1.2003292558651975,
        "wave": 231778.13524932915,
        "combined": 84407173.05766457,
        "compression": 84000305.8602074,
        "tipover": 543151.2017974482,
        "torque": 124206.12371752645
    },
    {
        "id": "c11843",
        "legs": 4,
        "total_height": 87.37244929648898,
        "radius_bottom": 21.564453478914743,
        "radius_top": 9.316306956374623,
        "n_layers": 4,
        "layer_heights": [
            13.960403394378055,
            17.056259084600164
        ],
        "connection_types": [
            "X",
            "X",
            "X"
        ],
        "Cost": 1472.7381136880074,
        "plausibility (FAMD GMM)": 4.092932618048804,
        "plausibility (FAMD Mahalanobis)": 1.4840376071464196,
        "plausibility (SVM)": -1.224146721171882,
        "plausibility (One Class SVM) gamma=scale nu=0.5": 1.3832652554673608,
        "plausibility (FAMD One Class SVM) gamma=scale nu=0.5": 2.163411777892682,
        "wave": 213131.66736287074,
        "combined": 32860877.000774227,
        "compression": 32213034.900147665,
        "tipover": 487210.548926433,
        "torque": 71038.00675235559
    }
]